{"timestamp":"2026-07-23T08:10:02.815926+00:00","block":8683175,"sum_prices":2.315851547,"subnets":{"1":{"name":"Apex","price":0.008575447,"equilibrium":0.012220528526843086,"distance_pct":-29.8,"emission_enabled":true,"cb_vs_pool":0.0,"tao_pool":26118.0},"2":{"name":"DSperse","price":0.005052573,"equilibrium":0.007046751134880109,"distance_pct":-28.3,"emission_enabled":true,"cb_vs_pool":0.0,"tao_pool":9916.0},"3":{"name":"deprecated","price":0.022347289,"equilibrium":0.032349800290243765,"distance_pct":-30.9,"emission_enabled":true,"cb_vs_pool":0.13,"tao_pool":69055.0},"4":{"name":"Targon","price":0.054622901,"equilibrium":0.0811340792430335,"distance_pct":-32.7,"emission_enabled":true,"cb_vs_pool":0.17,"tao_pool":133080.0},"5":{"name":"Hone","price":0.015416169,"equilibrium":0.021519575036048576,"distance_pct":-28.4,"emission_enabled":false,"cb_vs_pool":0.0,"tao_pool":36101.0},"6":{"name":"Numinous","price":0.003278724,"equilibrium":0.0045876920495791325,"distance_pct":-28.5,"emission_enabled":true,"cb_vs_pool":0.15,"tao_pool":8846.0},"7":{"name":"Allways","price":0.004183397,"equilibrium":0.005474038747177424,"distance_pct":-23.6,"emission_enabled":true,"cb_vs_pool":0.22,"tao_pool":7246.0},"8":{"name":"Vanta","price":0.027939693,"equilibrium":0.04050160024282476,"distance_pct":-31.0,"emission_enabled":true,"cb_vs_pool":0.0,"tao_pool":78155.0},"9":{"name":"iota","price":0.035065765,"equilibrium":0.05108967265184803,"distance_pct":-31.4,"emission_enabled":true,"cb_vs_pool":0.0,"tao_pool":61919.0},"10":{"name":"Swap","price":0.00653358,"equilibrium":0.009391271075310096,"distance_pct":-30.4,"emission_enabled":false,"cb_vs_pool":0.0,"tao_pool":16658.0},"11":{"name":"TrajectoryRL","price":0.008901176,"equilibrium":0.012728491893482729,"distance_pct":-30.1,"emission_enabled":true,"cb_vs_pool":0.17,"tao_pool":21136.0},"12":{"name":"Compute Horde","price":0.005451614,"equilibrium":0.008156871004632861,"distance_pct":-33.2,"emission_enabled":false,"cb_vs_pool":0.0,"tao_pool":13520.0},"13":{"name":"Data Universe","price":0.006922919,"equilibrium":0.010110572253456835,"distance_pct":-31.5,"emission_enabled":true,"cb_vs_pool":0.02,"tao_pool":22184.0},"14":{"name":"Cacheon","price":0.010119088,"equilibrium":0.014401644852948068,"distance_pct":-29.7,"emission_enabled":false,"cb_vs_pool":0.0,"tao_pool":26081.0},"15":{"name":"ORO","price":0.021095323,"equilibrium":0.01189678239303564,"distance_pct":77.3,"emission_enabled":true,"cb_vs_pool":0.55,"tao_pool":9288.0},"16":{"name":"Fast Thinker","price":0.00506102,"equilibrium":0.0014946182539109672,"distance_pct":238.6,"emission_enabled":false,"cb_vs_pool":0.0,"tao_pool":756.0},"17":{"name":"404\u2014GEN","price":0.010830689,"equilibrium":0.015523064535173997,"distance_pct":-30.2,"emission_enabled":true,"cb_vs_pool":0.04,"tao_pool":27532.0},"18":{"name":"Zeus","price":0.006496071,"equilibrium":0.009002490989646037,"distance_pct":-27.8,"emission_enabled":true,"cb_vs_pool":0.17,"tao_pool":12731.0},"19":{"name":"blockmachine","price":0.010130973,"equilibrium":0.014552915121387247,"distance_pct":-30.4,"emission_enabled":true,"cb_vs_pool":0.0,"tao_pool":31903.0},"20":{"name":"ChronoSeek","price":0.00338312,"equilibrium":0.004836037866315375,"distance_pct":-30.0,"emission_enabled":false,"cb_vs_pool":0.0,"tao_pool":7783.0},"21":{"name":"AdTAO","price":0.00414757,"equilibrium":0.005979723776407449,"distance_pct":-30.6,"emission_enabled":true,"cb_vs_pool":0.05,"tao_pool":8208.0},"22":{"name":"Desearch","price":0.003768049,"equilibrium":0.005504278309198829,"distance_pct":-31.5,"emission_enabled":true,"cb_vs_pool":0.06,"tao_pool":8404.0},"23":{"name":"Trishool","price":0.005812799,"equilibrium":0.00841765190878068,"distance_pct":-30.9,"emission_enabled":true,"cb_vs_pool":0.28,"tao_pool":8639.0},"24":{"name":"Quasar","price":0.008664016,"equilibrium":0.012389673399453368,"distance_pct":-30.1,"emission_enabled":true,"cb_vs_pool":0.28,"tao_pool":12635.0},"25":{"name":"Mainframe","price":0.007700071,"equilibrium":0.011099763146398068,"distance_pct":-30.6,"emission_enabled":false,"cb_vs_pool":0.0,"tao_pool":14187.0},"26":{"name":"Perturb","price":0.006412863,"equilibrium":0.0030136109097319698,"distance_pct":112.8,"emission_enabled":false,"cb_vs_pool":0.0,"tao_pool":2651.0},"27":{"name":"Orion","price":0.003959007,"equilibrium":0.005799230343371628,"distance_pct":-31.7,"emission_enabled":false,"cb_vs_pool":0.0,"tao_pool":8114.0},"28":{"name":"gm","price":0.01347229,"equilibrium":0.019631228230041795,"distance_pct":-31.4,"emission_enabled":true,"cb_vs_pool":0.05,"tao_pool":16995.0},"29":{"name":"ho\u03c4floa\u03c4","price":0.003341987,"equilibrium":0.004827759241047133,"distance_pct":-30.8,"emission_enabled":false,"cb_vs_pool":0.0,"tao_pool":9118.0},"30":{"name":"Endure Network","price":0.0042975,"equilibrium":0.0061658210886938415,"distance_pct":-30.3,"emission_enabled":false,"cb_vs_pool":0.0,"tao_pool":9560.0},"31":{"name":"rec4ll","price":0.004070568,"equilibrium":0.002543326964573789,"distance_pct":60.0,"emission_enabled":false,"cb_vs_pool":0.0,"tao_pool":1819.0},"32":{"name":"ItsAI","price":0.003440315,"equilibrium":0.0049977791195337795,"distance_pct":-31.2,"emission_enabled":true,"cb_vs_pool":0.18,"tao_pool":7647.0},"33":{"name":"ReadyAI","price":0.005893972,"equilibrium":0.007682985614890071,"distance_pct":-23.3,"emission_enabled":true,"cb_vs_pool":0.15,"tao_pool":16072.0},"34":{"name":"BitMind","price":0.012234253,"equilibrium":0.016692045480530132,"distance_pct":-26.7,"emission_enabled":true,"cb_vs_pool":0.14,"tao_pool":34679.0},"35":{"name":"OxMarkets","price":0.003346421,"equilibrium":0.004826644302860319,"distance_pct":-30.7,"emission_enabled":true,"cb_vs_pool":0.16,"tao_pool":8335.0},"36":{"name":"Eirel","price":0.003311006,"equilibrium":0.0014350498416082255,"distance_pct":130.7,"emission_enabled":true,"cb_vs_pool":0.46,"tao_pool":1098.0},"37":{"name":"Aurelius","price":0.00365121,"equilibrium":0.005322426845261624,"distance_pct":-31.4,"emission_enabled":false,"cb_vs_pool":0.0,"tao_pool":8333.0},"38":{"name":"ChronoLLM","price":0.011471704,"equilibrium":0.006853109142253818,"distance_pct":67.4,"emission_enabled":true,"cb_vs_pool":0.0,"tao_pool":4586.0},"39":{"name":"deprecated","price":0.006820193,"equilibrium":0.009963810967719292,"distance_pct":-31.6,"emission_enabled":true,"cb_vs_pool":0.0,"tao_pool":17417.0},"40":{"name":"Ralph","price":0.011302958,"equilibrium":0.003652241886544241,"distance_pct":209.5,"emission_enabled":false,"cb_vs_pool":0.0,"tao_pool":2629.0},"41":{"name":"Almanac","price":0.006155309,"equilibrium":0.00853861019145681,"distance_pct":-27.9,"emission_enabled":true,"cb_vs_pool":0.01,"tao_pool":13804.0},"42":{"name":"Unknown","price":0.003287838,"equilibrium":0.004526280355410888,"distance_pct":-27.4,"emission_enabled":false,"cb_vs_pool":0.0,"tao_pool":8478.0},"43":{"name":"Graphite","price":0.005419528,"equilibrium":0.007861089507519655,"distance_pct":-31.1,"emission_enabled":false,"cb_vs_pool":0.0,"tao_pool":14385.0},"44":{"name":"Score","price":0.033441464,"equilibrium":0.04777075631612438,"distance_pct":-30.0,"emission_enabled":true,"cb_vs_pool":0.16,"tao_pool":61304.0},"45":{"name":"AlphaRidge.ai","price":0.00320454,"equilibrium":0.004470600851294818,"distance_pct":-28.3,"emission_enabled":false,"cb_vs_pool":0.0,"tao_pool":7173.0},"46":{"name":"Zipcode","price":0.006184397,"equilibrium":0.008644244886981177,"distance_pct":-28.5,"emission_enabled":true,"cb_vs_pool":0.12,"tao_pool":11164.0},"47":{"name":"EvolAI","price":0.003405525,"equilibrium":0.0019352350039591177,"distance_pct":76.0,"emission_enabled":false,"cb_vs_pool":0.0,"tao_pool":1388.0},"48":{"name":"Quantum Compute","price":0.005576251,"equilibrium":0.007834579121611665,"distance_pct":-28.8,"emission_enabled":true,"cb_vs_pool":0.19,"tao_pool":12144.0},"49":{"name":"Nepher Robotics","price":0.007158274,"equilibrium":0.0052622880264124984,"distance_pct":36.0,"emission_enabled":true,"cb_vs_pool":0.62,"tao_pool":3402.0},"50":{"name":"Synth","price":0.005426229,"equilibrium":0.007514927760842128,"distance_pct":-27.8,"emission_enabled":true,"cb_vs_pool":0.07,"tao_pool":11543.0},"51":{"name":"lium.io","price":0.060576446,"equilibrium":0.08567146638869039,"distance_pct":-29.3,"emission_enabled":true,"cb_vs_pool":0.19,"tao_pool":126673.0},"52":{"name":"Dojo","price":0.007058494,"equilibrium":0.010160067544398289,"distance_pct":-30.5,"emission_enabled":false,"cb_vs_pool":0.0,"tao_pool":18927.0},"53":{"name":"engy","price":0.022149283,"equilibrium":0.03177748976643428,"distance_pct":-30.3,"emission_enabled":false,"cb_vs_pool":0.0,"tao_pool":28716.0},"54":{"name":"Yanez MIID","price":0.005398524,"equilibrium":0.007652864668004566,"distance_pct":-29.5,"emission_enabled":true,"cb_vs_pool":0.16,"tao_pool":9181.0},"55":{"name":"NIOME","price":0.00345092,"equilibrium":0.004611778175143311,"distance_pct":-25.2,"emission_enabled":true,"cb_vs_pool":0.19,"tao_pool":7398.0},"56":{"name":"Gradients","price":0.017320658,"equilibrium":0.025007920855978572,"distance_pct":-30.7,"emission_enabled":true,"cb_vs_pool":0.02,"tao_pool":52526.0},"57":{"name":"SN57","price":0.00654936,"equilibrium":0.002904307667696218,"distance_pct":125.5,"emission_enabled":false,"cb_vs_pool":0.0,"tao_pool":2065.0},"58":{"name":"greevils","price":0.009995239,"equilibrium":0.0027463441960639606,"distance_pct":263.9,"emission_enabled":false,"cb_vs_pool":0.0,"tao_pool":1086.0},"59":{"name":"Babelbit","price":0.003259871,"equilibrium":0.004682032166033132,"distance_pct":-30.4,"emission_enabled":true,"cb_vs_pool":0.2,"tao_pool":6486.0},"60":{"name":"Bitsec.ai","price":0.005162892,"equilibrium":0.007092647089608919,"distance_pct":-27.2,"emission_enabled":true,"cb_vs_pool":0.09,"tao_pool":7865.0},"61":{"name":"RedTeam","price":0.006031084,"equilibrium":0.008779658858108243,"distance_pct":-31.3,"emission_enabled":true,"cb_vs_pool":0.1,"tao_pool":9716.0},"62":{"name":"Ridges","price":0.011942645,"equilibrium":0.01590271926758991,"distance_pct":-24.9,"emission_enabled":false,"cb_vs_pool":0.0,"tao_pool":30938.0},"63":{"name":"Enigma","price":0.008901791,"equilibrium":0.012714009693496973,"distance_pct":-30.0,"emission_enabled":true,"cb_vs_pool":0.23,"tao_pool":15678.0},"64":{"name":"Chutes","price":0.080904076,"equilibrium":0.11986702171576007,"distance_pct":-32.5,"emission_enabled":true,"cb_vs_pool":0.16,"tao_pool":212000.0},"65":{"name":"TAO Private Network","price":0.003401094,"equilibrium":0.0048590573053743135,"distance_pct":-30.0,"emission_enabled":true,"cb_vs_pool":0.0,"tao_pool":7067.0},"66":{"name":"ninja","price":0.006535832,"equilibrium":0.009162435170087907,"distance_pct":-28.7,"emission_enabled":true,"cb_vs_pool":0.27,"tao_pool":9820.0},"67":{"name":"Harnyx","price":0.010299976,"equilibrium":0.00484240314304515,"distance_pct":112.7,"emission_enabled":true,"cb_vs_pool":0.18,"tao_pool":3743.0},"68":{"name":"NOVA","price":0.022013989,"equilibrium":0.0307467315806611,"distance_pct":-28.4,"emission_enabled":true,"cb_vs_pool":0.2,"tao_pool":43378.0},"69":{"name":"Herald","price":0.011505711,"equilibrium":0.0061756669291708885,"distance_pct":86.3,"emission_enabled":false,"cb_vs_pool":0.0,"tao_pool":5049.0},"70":{"name":"NexisGen","price":0.002873965,"equilibrium":0.00130552552629361,"distance_pct":120.1,"emission_enabled":false,"cb_vs_pool":0.0,"tao_pool":1070.0},"71":{"name":"Leadpoet","price":0.004588788,"equilibrium":0.006378892686647025,"distance_pct":-28.1,"emission_enabled":true,"cb_vs_pool":0.2,"tao_pool":5369.0},"72":{"name":"StreetVision by NATIX","price":0.003154951,"equilibrium":0.004154901935362003,"distance_pct":-24.1,"emission_enabled":false,"cb_vs_pool":0.0,"tao_pool":7533.0},"73":{"name":"Parked","price":0.003462492,"equilibrium":0.004782353750596514,"distance_pct":-27.6,"emission_enabled":false,"cb_vs_pool":0.0,"tao_pool":7232.0},"74":{"name":"Gittensor","price":0.005238188,"equilibrium":0.0067937649146873865,"distance_pct":-22.9,"emission_enabled":true,"cb_vs_pool":0.28,"tao_pool":7530.0},"75":{"name":"Hippius","price":0.015476309,"equilibrium":0.020894005911725036,"distance_pct":-25.9,"emission_enabled":true,"cb_vs_pool":0.0,"tao_pool":30674.0},"76":{"name":"Byzantium","price":0.002949212,"equilibrium":0.0015034436580334991,"distance_pct":96.2,"emission_enabled":false,"cb_vs_pool":0.0,"tao_pool":1213.0},"77":{"name":"Liquidity","price":0.006600723,"equilibrium":0.008870675815926243,"distance_pct":-25.6,"emission_enabled":false,"cb_vs_pool":0.0,"tao_pool":12998.0},"78":{"name":"Vocence","price":0.004986603,"equilibrium":0.0020947797001674116,"distance_pct":138.0,"emission_enabled":true,"cb_vs_pool":0.52,"tao_pool":1483.0},"79":{"name":"MVTRX","price":0.00794424,"equilibrium":0.010013503349082041,"distance_pct":-20.7,"emission_enabled":true,"cb_vs_pool":0.29,"tao_pool":10747.0},"80":{"name":"unknown","price":0.003381359,"equilibrium":0.002117110933661704,"distance_pct":59.7,"emission_enabled":false,"cb_vs_pool":0.0,"tao_pool":1456.0},"81":{"name":"deprecated","price":0.008664827,"equilibrium":0.01140228058363774,"distance_pct":-24.0,"emission_enabled":true,"cb_vs_pool":0.16,"tao_pool":20865.0},"82":{"name":"Compelle","price":0.006339676,"equilibrium":0.0025597245897137494,"distance_pct":147.7,"emission_enabled":true,"cb_vs_pool":0.47,"tao_pool":1943.0},"83":{"name":"CliqueAI","price":0.011331593,"equilibrium":0.01082890600046754,"distance_pct":4.6,"emission_enabled":false,"cb_vs_pool":0.0,"tao_pool":9242.0},"84":{"name":"SN84","price":0.002941308,"equilibrium":0.001309027741219646,"distance_pct":124.7,"emission_enabled":false,"cb_vs_pool":0.0,"tao_pool":1613.0},"85":{"name":"Vidaio","price":0.006451436,"equilibrium":0.008176142756248313,"distance_pct":-21.1,"emission_enabled":true,"cb_vs_pool":0.18,"tao_pool":13932.0},"86":{"name":"\u2692","price":0.002647329,"equilibrium":0.0018799495934883471,"distance_pct":40.8,"emission_enabled":false,"cb_vs_pool":0.0,"tao_pool":1879.0},"87":{"name":"Provenonce","price":0.004866917,"equilibrium":0.0029796502680065383,"distance_pct":63.3,"emission_enabled":false,"cb_vs_pool":0.0,"tao_pool":1825.0},"88":{"name":"Investing","price":0.003362189,"equilibrium":0.004299255062601456,"distance_pct":-21.8,"emission_enabled":true,"cb_vs_pool":0.21,"tao_pool":6352.0},"89":{"name":"InfiniteQuant","price":0.003997692,"equilibrium":0.004788791458459832,"distance_pct":-16.5,"emission_enabled":true,"cb_vs_pool":0.01,"tao_pool":6990.0},"90":{"name":"KubeTEE AI Factory","price":0.006701824,"equilibrium":0.0044056421721161655,"distance_pct":52.1,"emission_enabled":false,"cb_vs_pool":0.0,"tao_pool":1005.0},"91":{"name":"cascade","price":0.013377779,"equilibrium":0.006462364414402354,"distance_pct":107.0,"emission_enabled":false,"cb_vs_pool":0.0,"tao_pool":3846.0},"92":{"name":"wgmi","price":0.005985308,"equilibrium":0.001962718599118529,"distance_pct":204.9,"emission_enabled":false,"cb_vs_pool":0.0,"tao_pool":1216.0},"93":{"name":"Bitcast","price":0.01041848,"equilibrium":0.01293151954374613,"distance_pct":-19.4,"emission_enabled":true,"cb_vs_pool":0.05,"tao_pool":16928.0},"94":{"name":"pending...","price":0.006781207,"equilibrium":0.004495989797555954,"distance_pct":50.8,"emission_enabled":true,"cb_vs_pool":0.0,"tao_pool":2818.0},"95":{"name":"Actual","price":0.046578813,"equilibrium":0.04318558773095242,"distance_pct":7.9,"emission_enabled":false,"cb_vs_pool":0.0,"tao_pool":28673.0},"96":{"name":"Verathos","price":0.013928708,"equilibrium":0.005703135243979793,"distance_pct":144.2,"emission_enabled":true,"cb_vs_pool":0.52,"tao_pool":3786.0},"97":{"name":"Albedo","price":0.026683159,"equilibrium":0.01278506523004172,"distance_pct":108.7,"emission_enabled":true,"cb_vs_pool":0.5,"tao_pool":9913.0},"98":{"name":"NeverPlayAlone","price":0.003301512,"equilibrium":0.00395073575162041,"distance_pct":-16.4,"emission_enabled":false,"cb_vs_pool":0.0,"tao_pool":5617.0},"99":{"name":"Thirty Spokes","price":0.00821036,"equilibrium":0.0021972637719938964,"distance_pct":273.7,"emission_enabled":false,"cb_vs_pool":0.0,"tao_pool":946.0},"100":{"name":"BASE","price":0.007049002,"equilibrium":0.004841738337111656,"distance_pct":45.6,"emission_enabled":true,"cb_vs_pool":0.0,"tao_pool":3223.0},"101":{"name":"Tag101","price":0.005093046,"equilibrium":0.00449756138305118,"distance_pct":13.2,"emission_enabled":false,"cb_vs_pool":0.0,"tao_pool":4197.0},"102":{"name":"ConnitoAI","price":0.008934136,"equilibrium":0.004018549164765881,"distance_pct":122.3,"emission_enabled":true,"cb_vs_pool":0.11,"tao_pool":3510.0},"103":{"name":"Djinn","price":0.003262678,"equilibrium":0.0035179422770617143,"distance_pct":-7.3,"emission_enabled":true,"cb_vs_pool":0.3,"tao_pool":4095.0},"104":{"name":"Masx.ai","price":0.005039314,"equilibrium":0.005940284506119058,"distance_pct":-15.2,"emission_enabled":false,"cb_vs_pool":0.0,"tao_pool":6518.0},"105":{"name":"Beam","price":0.009563333,"equilibrium":0.007122779375354625,"distance_pct":34.3,"emission_enabled":true,"cb_vs_pool":0.55,"tao_pool":5286.0},"106":{"name":"Nodexo","price":0.004123597,"equilibrium":0.00492262637786827,"distance_pct":-16.2,"emission_enabled":true,"cb_vs_pool":0.01,"tao_pool":7742.0},"107":{"name":"Minos","price":0.044106337,"equilibrium":0.024482175736657397,"distance_pct":80.2,"emission_enabled":true,"cb_vs_pool":0.75,"tao_pool":13806.0},"108":{"name":"TalkHead","price":0.004008019,"equilibrium":0.002648517177574089,"distance_pct":51.3,"emission_enabled":false,"cb_vs_pool":0.0,"tao_pool":2224.0},"109":{"name":"GuardArena","price":0.003216695,"equilibrium":0.0019236311392522591,"distance_pct":67.2,"emission_enabled":false,"cb_vs_pool":0.0,"tao_pool":1483.0},"110":{"name":"Green Compute","price":0.008928852,"equilibrium":0.007978005645118568,"distance_pct":11.9,"emission_enabled":false,"cb_vs_pool":0.0,"tao_pool":5575.0},"111":{"name":"Claims","price":0.005762801,"equilibrium":0.006831656506322613,"distance_pct":-15.6,"emission_enabled":false,"cb_vs_pool":0.0,"tao_pool":6278.0},"112":{"name":"minotaur","price":0.004185025,"equilibrium":0.003810231073804744,"distance_pct":9.8,"emission_enabled":true,"cb_vs_pool":0.2,"tao_pool":4600.0},"113":{"name":"TensorUSD","price":0.00366224,"equilibrium":0.002388140377728166,"distance_pct":53.4,"emission_enabled":false,"cb_vs_pool":0.0,"tao_pool":2201.0},"114":{"name":"SOMA","price":0.012380864,"equilibrium":0.0071990504210929325,"distance_pct":72.0,"emission_enabled":true,"cb_vs_pool":0.67,"tao_pool":4734.0},"115":{"name":"HashiChain","price":0.004154183,"equilibrium":0.0033570641036003634,"distance_pct":23.7,"emission_enabled":false,"cb_vs_pool":0.0,"tao_pool":4481.0},"116":{"name":"Memo","price":0.02808711,"equilibrium":0.009694006450773571,"distance_pct":189.7,"emission_enabled":false,"cb_vs_pool":0.0,"tao_pool":3110.0},"117":{"name":"glyph","price":0.00404957,"equilibrium":0.003142505277566823,"distance_pct":28.9,"emission_enabled":true,"cb_vs_pool":0.0,"tao_pool":3575.0},"118":{"name":"Ditto","price":0.014497534,"equilibrium":0.011243552744003113,"distance_pct":28.9,"emission_enabled":true,"cb_vs_pool":0.6,"tao_pool":7623.0},"119":{"name":"Satori","price":0.004046405,"equilibrium":0.0031122846477235604,"distance_pct":30.0,"emission_enabled":false,"cb_vs_pool":0.0,"tao_pool":4108.0},"120":{"name":"Affine","price":0.053188379,"equilibrium":0.05595655769514094,"distance_pct":-4.9,"emission_enabled":true,"cb_vs_pool":0.25,"tao_pool":77558.0},"121":{"name":"sundae_bar","price":0.005611928,"equilibrium":0.006120892465444844,"distance_pct":-8.3,"emission_enabled":true,"cb_vs_pool":0.0,"tao_pool":6951.0},"122":{"name":"CookingTAO","price":0.008410654,"equilibrium":0.003039326323998891,"distance_pct":176.7,"emission_enabled":false,"cb_vs_pool":0.0,"tao_pool":1934.0},"123":{"name":"MANTIS","price":0.003401907,"equilibrium":0.003709779070733538,"distance_pct":-8.3,"emission_enabled":true,"cb_vs_pool":0.08,"tao_pool":6826.0},"124":{"name":"Swarm","price":0.009623166,"equilibrium":0.011218664432577406,"distance_pct":-14.2,"emission_enabled":true,"cb_vs_pool":0.1,"tao_pool":11314.0},"125":{"name":"8 Ball","price":0.003501809,"equilibrium":0.0038415033450567987,"distance_pct":-8.8,"emission_enabled":false,"cb_vs_pool":0.0,"tao_pool":6131.0},"126":{"name":"Poker44","price":0.006879433,"equilibrium":0.0037102997766858287,"distance_pct":85.4,"emission_enabled":true,"cb_vs_pool":0.59,"tao_pool":2885.0},"127":{"name":"Astrid","price":0.003805024,"equilibrium":0.004007284784778228,"distance_pct":-5.0,"emission_enabled":true,"cb_vs_pool":0.0,"tao_pool":3857.0},"128":{"name":"ByteLeap","price":0.003808036,"equilibrium":0.004126422571912044,"distance_pct":-7.7,"emission_enabled":false,"cb_vs_pool":0.0,"tao_pool":4670.0}}}