{"timestamp":"2026-07-23T17:35:02.444818+00:00","block":8685999,"sum_prices":2.310897472,"subnets":{"1":{"name":"Apex","price":0.008567693,"equilibrium":0.012249612571229607,"distance_pct":-30.1,"emission_enabled":true,"cb_vs_pool":0.0,"tao_pool":26108.0},"2":{"name":"DSperse","price":0.005141614,"equilibrium":0.00719468563327549,"distance_pct":-28.5,"emission_enabled":true,"cb_vs_pool":0.0,"tao_pool":10005.0},"3":{"name":"deprecated","price":0.022369587,"equilibrium":0.032488902009294184,"distance_pct":-31.1,"emission_enabled":true,"cb_vs_pool":0.13,"tao_pool":69099.0},"4":{"name":"Targon","price":0.055221798,"equilibrium":0.08229428709676331,"distance_pct":-32.9,"emission_enabled":true,"cb_vs_pool":0.17,"tao_pool":133830.0},"5":{"name":"Hone","price":0.015258712,"equilibrium":0.021369173844614356,"distance_pct":-28.6,"emission_enabled":false,"cb_vs_pool":0.0,"tao_pool":35917.0},"6":{"name":"Numinous","price":0.003227567,"equilibrium":0.004531000491077463,"distance_pct":-28.8,"emission_enabled":true,"cb_vs_pool":0.15,"tao_pool":8778.0},"7":{"name":"Allways","price":0.004280832,"equilibrium":0.005620345657147313,"distance_pct":-23.8,"emission_enabled":true,"cb_vs_pool":0.22,"tao_pool":7332.0},"8":{"name":"Vanta","price":0.027921262,"equilibrium":0.040606804536541356,"distance_pct":-31.2,"emission_enabled":true,"cb_vs_pool":0.0,"tao_pool":78131.0},"9":{"name":"iota","price":0.03464824,"equilibrium":0.05064726787903144,"distance_pct":-31.6,"emission_enabled":true,"cb_vs_pool":0.0,"tao_pool":61560.0},"10":{"name":"Swap","price":0.006593762,"equilibrium":0.00950856629344212,"distance_pct":-30.7,"emission_enabled":false,"cb_vs_pool":0.0,"tao_pool":16735.0},"11":{"name":"TrajectoryRL","price":0.008759957,"equilibrium":0.012568094121125764,"distance_pct":-30.3,"emission_enabled":true,"cb_vs_pool":0.17,"tao_pool":20972.0},"12":{"name":"Compute Horde","price":0.005463611,"equilibrium":0.008201277530783981,"distance_pct":-33.4,"emission_enabled":false,"cb_vs_pool":0.0,"tao_pool":13535.0},"13":{"name":"Data Universe","price":0.006901735,"equilibrium":0.010112967219112862,"distance_pct":-31.8,"emission_enabled":true,"cb_vs_pool":0.02,"tao_pool":22153.0},"14":{"name":"Cacheon","price":0.010116686,"equilibrium":0.014445047901825695,"distance_pct":-30.0,"emission_enabled":false,"cb_vs_pool":0.0,"tao_pool":26077.0},"15":{"name":"ORO","price":0.020132781,"equilibrium":0.011399294468628847,"distance_pct":76.6,"emission_enabled":true,"cb_vs_pool":0.57,"tao_pool":9096.0},"16":{"name":"Fast Thinker","price":0.004919129,"equilibrium":0.0014592118260466417,"distance_pct":237.1,"emission_enabled":false,"cb_vs_pool":0.0,"tao_pool":745.0},"17":{"name":"404\u2014GEN","price":0.010898664,"equilibrium":0.015672276496176363,"distance_pct":-30.5,"emission_enabled":true,"cb_vs_pool":0.04,"tao_pool":27623.0},"18":{"name":"Zeus","price":0.006483434,"equilibrium":0.009014904823892717,"distance_pct":-28.1,"emission_enabled":true,"cb_vs_pool":0.17,"tao_pool":12721.0},"19":{"name":"blockmachine","price":0.010125743,"equilibrium":0.014593066263002386,"distance_pct":-30.6,"emission_enabled":true,"cb_vs_pool":0.0,"tao_pool":31896.0},"20":{"name":"ChronoSeek","price":0.003408126,"equilibrium":0.00488761872934904,"distance_pct":-30.3,"emission_enabled":false,"cb_vs_pool":0.0,"tao_pool":7812.0},"21":{"name":"AdTAO","price":0.004094871,"equilibrium":0.005923236726925559,"distance_pct":-30.9,"emission_enabled":true,"cb_vs_pool":0.05,"tao_pool":8157.0},"22":{"name":"Desearch","price":0.003770177,"equilibrium":0.005525598914747175,"distance_pct":-31.8,"emission_enabled":true,"cb_vs_pool":0.06,"tao_pool":8408.0},"23":{"name":"Trishool","price":0.005777845,"equilibrium":0.008394735084866423,"distance_pct":-31.2,"emission_enabled":true,"cb_vs_pool":0.27,"tao_pool":8616.0},"24":{"name":"Quasar","price":0.008602583,"equilibrium":0.012342620131823013,"distance_pct":-30.3,"emission_enabled":true,"cb_vs_pool":0.27,"tao_pool":12594.0},"25":{"name":"Mainframe","price":0.008432911,"equilibrium":0.012195643891551705,"distance_pct":-30.9,"emission_enabled":false,"cb_vs_pool":0.0,"tao_pool":14831.0},"26":{"name":"Perturb","price":0.006223866,"equilibrium":0.0029361589458178246,"distance_pct":112.0,"emission_enabled":false,"cb_vs_pool":0.0,"tao_pool":2612.0},"27":{"name":"Orion","price":0.003785596,"equilibrium":0.005563196610035154,"distance_pct":-32.0,"emission_enabled":false,"cb_vs_pool":0.0,"tao_pool":7934.0},"28":{"name":"gm","price":0.01320758,"equilibrium":0.01930912492704139,"distance_pct":-31.6,"emission_enabled":true,"cb_vs_pool":0.08,"tao_pool":16832.0},"29":{"name":"ho\u03c4floa\u03c4","price":0.003344953,"equilibrium":0.004847734242127851,"distance_pct":-31.0,"emission_enabled":false,"cb_vs_pool":0.0,"tao_pool":9122.0},"30":{"name":"Endure Network","price":0.004121053,"equilibrium":0.005931876563246418,"distance_pct":-30.5,"emission_enabled":false,"cb_vs_pool":0.0,"tao_pool":9361.0},"31":{"name":"rec4ll","price":0.004052779,"equilibrium":0.002541480574748231,"distance_pct":59.5,"emission_enabled":false,"cb_vs_pool":0.0,"tao_pool":1815.0},"32":{"name":"ItsAI","price":0.00346177,"equilibrium":0.005045436567385988,"distance_pct":-31.4,"emission_enabled":true,"cb_vs_pool":0.18,"tao_pool":7673.0},"33":{"name":"ReadyAI","price":0.005901068,"equilibrium":0.007717809786804957,"distance_pct":-23.5,"emission_enabled":true,"cb_vs_pool":0.14,"tao_pool":16085.0},"34":{"name":"BitMind","price":0.012213418,"equilibrium":0.016719243745649013,"distance_pct":-26.9,"emission_enabled":true,"cb_vs_pool":0.14,"tao_pool":34655.0},"35":{"name":"OxMarkets","price":0.003299031,"equilibrium":0.0047740541067979305,"distance_pct":-30.9,"emission_enabled":true,"cb_vs_pool":0.16,"tao_pool":8277.0},"36":{"name":"Eirel","price":0.003297838,"equilibrium":0.0014360590465398325,"distance_pct":129.6,"emission_enabled":true,"cb_vs_pool":0.45,"tao_pool":1101.0},"37":{"name":"Aurelius","price":0.003652806,"equilibrium":0.0053420285477328985,"distance_pct":-31.6,"emission_enabled":false,"cb_vs_pool":0.0,"tao_pool":8335.0},"38":{"name":"ChronoLLM","price":0.011638752,"equilibrium":0.006981052746023603,"distance_pct":66.7,"emission_enabled":true,"cb_vs_pool":0.63,"tao_pool":4630.0},"39":{"name":"deprecated","price":0.006838948,"equilibrium":0.010023618723321644,"distance_pct":-31.8,"emission_enabled":true,"cb_vs_pool":0.0,"tao_pool":17441.0},"40":{"name":"Ralph","price":0.010858342,"equilibrium":0.003523802441439776,"distance_pct":208.1,"emission_enabled":false,"cb_vs_pool":0.0,"tao_pool":2577.0},"41":{"name":"Almanac","price":0.00613629,"equilibrium":0.008540575403079157,"distance_pct":-28.2,"emission_enabled":true,"cb_vs_pool":0.02,"tao_pool":13785.0},"42":{"name":"Unknown","price":0.003287461,"equilibrium":0.004540527512819328,"distance_pct":-27.6,"emission_enabled":false,"cb_vs_pool":0.0,"tao_pool":8478.0},"43":{"name":"Graphite","price":0.005419296,"equilibrium":0.007886268239569375,"distance_pct":-31.3,"emission_enabled":false,"cb_vs_pool":0.0,"tao_pool":14385.0},"44":{"name":"Score","price":0.032344121,"equilibrium":0.0463564469201266,"distance_pct":-30.2,"emission_enabled":true,"cb_vs_pool":0.16,"tao_pool":60303.0},"45":{"name":"AlphaRidge.ai","price":0.00319522,"equilibrium":0.0044721226883235,"distance_pct":-28.6,"emission_enabled":false,"cb_vs_pool":0.0,"tao_pool":7162.0},"46":{"name":"Zipcode","price":0.00606777,"equilibrium":0.008509444521364179,"distance_pct":-28.7,"emission_enabled":true,"cb_vs_pool":0.11,"tao_pool":11061.0},"47":{"name":"EvolAI","price":0.003381925,"equilibrium":0.0019289973917411061,"distance_pct":75.3,"emission_enabled":false,"cb_vs_pool":0.0,"tao_pool":1384.0},"48":{"name":"Quantum Compute","price":0.005540457,"equilibrium":0.007810166745569492,"distance_pct":-29.1,"emission_enabled":true,"cb_vs_pool":0.18,"tao_pool":12108.0},"49":{"name":"Nepher Robotics","price":0.006895185,"equilibrium":0.00508814644840754,"distance_pct":35.5,"emission_enabled":true,"cb_vs_pool":0.64,"tao_pool":3345.0},"50":{"name":"Synth","price":0.005375244,"equilibrium":0.007467497332890912,"distance_pct":-28.0,"emission_enabled":true,"cb_vs_pool":0.19,"tao_pool":11490.0},"51":{"name":"lium.io","price":0.060477921,"equilibrium":0.08581598811569027,"distance_pct":-29.5,"emission_enabled":true,"cb_vs_pool":0.19,"tao_pool":126596.0},"52":{"name":"Dojo","price":0.007052623,"equilibrium":0.010184592496608094,"distance_pct":-30.8,"emission_enabled":false,"cb_vs_pool":0.0,"tao_pool":18920.0},"53":{"name":"engy","price":0.022157651,"equilibrium":0.03189279082479777,"distance_pct":-30.5,"emission_enabled":false,"cb_vs_pool":0.0,"tao_pool":28721.0},"54":{"name":"Yanez MIID","price":0.005461194,"equilibrium":0.007767408260384191,"distance_pct":-29.7,"emission_enabled":true,"cb_vs_pool":0.15,"tao_pool":9236.0},"55":{"name":"NIOME","price":0.003448962,"equilibrium":0.004624593864353429,"distance_pct":-25.4,"emission_enabled":true,"cb_vs_pool":0.18,"tao_pool":7398.0},"56":{"name":"Gradients","price":0.017235886,"equilibrium":0.024967947513012963,"distance_pct":-31.0,"emission_enabled":true,"cb_vs_pool":0.02,"tao_pool":52404.0},"57":{"name":"SN57","price":0.006530068,"equilibrium":0.002907213523199252,"distance_pct":124.6,"emission_enabled":false,"cb_vs_pool":0.0,"tao_pool":2062.0},"58":{"name":"greevils","price":0.01003102,"equilibrium":0.002768819082305568,"distance_pct":262.3,"emission_enabled":false,"cb_vs_pool":0.0,"tao_pool":1088.0},"59":{"name":"Babelbit","price":0.002964572,"equilibrium":0.004272017408305162,"distance_pct":-30.6,"emission_enabled":true,"cb_vs_pool":0.21,"tao_pool":6186.0},"60":{"name":"Bitsec.ai","price":0.005173637,"equilibrium":0.007131110627427618,"distance_pct":-27.4,"emission_enabled":true,"cb_vs_pool":0.09,"tao_pool":7875.0},"61":{"name":"RedTeam","price":0.006116207,"equilibrium":0.008933030597809907,"distance_pct":-31.5,"emission_enabled":true,"cb_vs_pool":0.09,"tao_pool":9787.0},"62":{"name":"Ridges","price":0.011851567,"equilibrium":0.015830011454649965,"distance_pct":-25.1,"emission_enabled":false,"cb_vs_pool":0.0,"tao_pool":30820.0},"63":{"name":"Enigma","price":0.009027497,"equilibrium":0.012936316351776786,"distance_pct":-30.2,"emission_enabled":true,"cb_vs_pool":0.23,"tao_pool":15792.0},"64":{"name":"Chutes","price":0.081771674,"equilibrium":0.12155234612611962,"distance_pct":-32.7,"emission_enabled":true,"cb_vs_pool":0.15,"tao_pool":213167.0},"65":{"name":"TAO Private Network","price":0.00340057,"equilibrium":0.004874101450689347,"distance_pct":-30.2,"emission_enabled":true,"cb_vs_pool":0.0,"tao_pool":7067.0},"66":{"name":"ninja","price":0.006406428,"equilibrium":0.009010175885487536,"distance_pct":-28.9,"emission_enabled":true,"cb_vs_pool":0.27,"tao_pool":9725.0},"67":{"name":"Harnyx","price":0.010143938,"equilibrium":0.0047899531152581845,"distance_pct":111.8,"emission_enabled":true,"cb_vs_pool":0.18,"tao_pool":3728.0},"68":{"name":"NOVA","price":0.020809287,"equilibrium":0.029160240044512453,"distance_pct":-28.6,"emission_enabled":true,"cb_vs_pool":0.21,"tao_pool":42183.0},"69":{"name":"Herald","price":0.011462773,"equilibrium":0.006175874390494149,"distance_pct":85.6,"emission_enabled":false,"cb_vs_pool":0.0,"tao_pool":5039.0},"70":{"name":"NexisGen","price":0.002931804,"equilibrium":0.001337037961401635,"distance_pct":119.3,"emission_enabled":false,"cb_vs_pool":0.0,"tao_pool":1080.0},"71":{"name":"Leadpoet","price":0.004679265,"equilibrium":0.0065263212482536866,"distance_pct":-28.3,"emission_enabled":true,"cb_vs_pool":0.1,"tao_pool":5424.0},"72":{"name":"StreetVision by NATIX","price":0.003133462,"equilibrium":0.004140127601984466,"distance_pct":-24.3,"emission_enabled":false,"cb_vs_pool":0.0,"tao_pool":7507.0},"73":{"name":"Parked","price":0.003461851,"equilibrium":0.00479706371862424,"distance_pct":-27.8,"emission_enabled":false,"cb_vs_pool":0.0,"tao_pool":7232.0},"74":{"name":"Gittensor","price":0.005173138,"equilibrium":0.006731786466039863,"distance_pct":-23.2,"emission_enabled":true,"cb_vs_pool":0.27,"tao_pool":7486.0},"75":{"name":"Hippius","price":0.015404631,"equilibrium":0.020865498627305676,"distance_pct":-26.2,"emission_enabled":true,"cb_vs_pool":0.0,"tao_pool":30604.0},"76":{"name":"Byzantium","price":0.002942378,"equilibrium":0.0015056962868171579,"distance_pct":95.4,"emission_enabled":false,"cb_vs_pool":0.0,"tao_pool":1211.0},"77":{"name":"Liquidity","price":0.006590535,"equilibrium":0.008885951959181708,"distance_pct":-25.8,"emission_enabled":false,"cb_vs_pool":0.0,"tao_pool":12988.0},"78":{"name":"Vocence","price":0.005089962,"equilibrium":0.0021484145615639854,"distance_pct":136.9,"emission_enabled":true,"cb_vs_pool":0.46,"tao_pool":1506.0},"79":{"name":"MVTRX","price":0.007631959,"equilibrium":0.009651806003825144,"distance_pct":-20.9,"emission_enabled":true,"cb_vs_pool":0.29,"tao_pool":10537.0},"80":{"name":"unknown","price":0.003997139,"equilibrium":0.002511815497311485,"distance_pct":59.1,"emission_enabled":false,"cb_vs_pool":0.0,"tao_pool":1583.0},"81":{"name":"deprecated","price":0.008677663,"equilibrium":0.011457497460662713,"distance_pct":-24.3,"emission_enabled":true,"cb_vs_pool":0.16,"tao_pool":20885.0},"82":{"name":"Compelle","price":0.006359052,"equilibrium":0.002580090651143638,"distance_pct":146.5,"emission_enabled":true,"cb_vs_pool":0.42,"tao_pool":1955.0},"83":{"name":"CliqueAI","price":0.011325133,"equilibrium":0.010859557359241467,"distance_pct":4.3,"emission_enabled":false,"cb_vs_pool":0.0,"tao_pool":9240.0},"84":{"name":"SN84","price":0.002948518,"equilibrium":0.0013174256829761907,"distance_pct":123.8,"emission_enabled":false,"cb_vs_pool":0.0,"tao_pool":1615.0},"85":{"name":"Vidaio","price":0.006360031,"equilibrium":0.008087509995721024,"distance_pct":-21.4,"emission_enabled":true,"cb_vs_pool":0.18,"tao_pool":13836.0},"86":{"name":"\u2692","price":0.002629916,"equilibrium":0.0018742572053710499,"distance_pct":40.3,"emission_enabled":false,"cb_vs_pool":0.0,"tao_pool":1873.0},"87":{"name":"Provenonce","price":0.004803139,"equilibrium":0.002951411723770292,"distance_pct":62.7,"emission_enabled":false,"cb_vs_pool":0.0,"tao_pool":1814.0},"88":{"name":"Investing","price":0.003233045,"equilibrium":0.0041480385796228165,"distance_pct":-22.1,"emission_enabled":true,"cb_vs_pool":0.21,"tao_pool":6230.0},"89":{"name":"InfiniteQuant","price":0.003995195,"equilibrium":0.004802034109408254,"distance_pct":-16.8,"emission_enabled":true,"cb_vs_pool":0.0,"tao_pool":6989.0},"90":{"name":"KubeTEE AI Factory","price":0.006701824,"equilibrium":0.004415086936329324,"distance_pct":51.8,"emission_enabled":false,"cb_vs_pool":0.0,"tao_pool":1005.0},"91":{"name":"cascade","price":0.013367845,"equilibrium":0.006481951098079477,"distance_pct":106.2,"emission_enabled":false,"cb_vs_pool":0.0,"tao_pool":3846.0},"92":{"name":"wgmi","price":0.006001897,"equilibrium":0.0019766594972709163,"distance_pct":203.6,"emission_enabled":false,"cb_vs_pool":0.0,"tao_pool":1217.0},"93":{"name":"Bitcast","price":0.010393984,"equilibrium":0.012944807873520212,"distance_pct":-19.7,"emission_enabled":true,"cb_vs_pool":0.05,"tao_pool":16913.0},"94":{"name":"pending...","price":0.005380508,"equilibrium":0.0035802249115296715,"distance_pct":50.3,"emission_enabled":true,"cb_vs_pool":0.0,"tao_pool":2508.0},"95":{"name":"Actual","price":0.046788726,"equilibrium":0.04352871160047121,"distance_pct":7.5,"emission_enabled":false,"cb_vs_pool":0.0,"tao_pool":28737.0},"96":{"name":"Verathos","price":0.01272296,"equilibrium":0.005234603125384464,"distance_pct":143.1,"emission_enabled":true,"cb_vs_pool":0.6,"tao_pool":3638.0},"97":{"name":"Albedo","price":0.026759048,"equilibrium":0.012877747833108705,"distance_pct":107.8,"emission_enabled":true,"cb_vs_pool":0.48,"tao_pool":9961.0},"98":{"name":"NeverPlayAlone","price":0.003303228,"equilibrium":0.003965884241700178,"distance_pct":-16.7,"emission_enabled":false,"cb_vs_pool":0.0,"tao_pool":5619.0},"99":{"name":"Thirty Spokes","price":0.009256866,"equilibrium":0.002488804454200248,"distance_pct":271.9,"emission_enabled":false,"cb_vs_pool":0.0,"tao_pool":1005.0},"100":{"name":"BASE","price":0.006980466,"equilibrium":0.0048118987822267055,"distance_pct":45.1,"emission_enabled":true,"cb_vs_pool":0.0,"tao_pool":3207.0},"101":{"name":"Tag101","price":0.005088774,"equilibrium":0.004509156805303861,"distance_pct":12.9,"emission_enabled":false,"cb_vs_pool":0.0,"tao_pool":4196.0},"102":{"name":"ConnitoAI","price":0.008843708,"equilibrium":0.0039959502726051865,"distance_pct":121.3,"emission_enabled":true,"cb_vs_pool":0.0,"tao_pool":3503.0},"103":{"name":"Djinn","price":0.003171031,"equilibrium":0.0034309913707633675,"distance_pct":-7.6,"emission_enabled":true,"cb_vs_pool":0.3,"tao_pool":4038.0},"104":{"name":"Masx.ai","price":0.005062102,"equilibrium":0.00598568887079774,"distance_pct":-15.4,"emission_enabled":false,"cb_vs_pool":0.0,"tao_pool":6533.0},"105":{"name":"Beam","price":0.009269284,"equilibrium":0.006929911240829694,"distance_pct":33.8,"emission_enabled":true,"cb_vs_pool":0.55,"tao_pool":5211.0},"106":{"name":"Nodexo","price":0.004296336,"equilibrium":0.005146318079713257,"distance_pct":-16.5,"emission_enabled":true,"cb_vs_pool":0.2,"tao_pool":7904.0},"107":{"name":"Minos","price":0.045788364,"equilibrium":0.025522076810491127,"distance_pct":79.4,"emission_enabled":true,"cb_vs_pool":0.7,"tao_pool":14117.0},"108":{"name":"TalkHead","price":0.003915138,"equilibrium":0.0025965088054861326,"distance_pct":50.8,"emission_enabled":false,"cb_vs_pool":0.0,"tao_pool":2198.0},"109":{"name":"GuardArena","price":0.003262045,"equilibrium":0.0019579555164489,"distance_pct":66.6,"emission_enabled":false,"cb_vs_pool":0.0,"tao_pool":1494.0},"110":{"name":"Green Compute","price":0.009142634,"equilibrium":0.008197137394974754,"distance_pct":11.5,"emission_enabled":false,"cb_vs_pool":0.0,"tao_pool":5641.0},"111":{"name":"Claims","price":0.005675617,"equilibrium":0.006750615968908901,"distance_pct":-15.9,"emission_enabled":false,"cb_vs_pool":0.0,"tao_pool":6231.0},"112":{"name":"minotaur","price":0.004213767,"equilibrium":0.0038501889046855973,"distance_pct":9.4,"emission_enabled":true,"cb_vs_pool":0.19,"tao_pool":4618.0},"113":{"name":"TensorUSD","price":0.003664917,"equilibrium":0.002398561340138795,"distance_pct":52.8,"emission_enabled":false,"cb_vs_pool":0.0,"tao_pool":2202.0},"114":{"name":"SOMA","price":0.012467431,"equilibrium":0.007278827135886165,"distance_pct":71.3,"emission_enabled":true,"cb_vs_pool":0.64,"tao_pool":4764.0},"115":{"name":"HashiChain","price":0.00417127,"equilibrium":0.0033826542682797982,"distance_pct":23.3,"emission_enabled":false,"cb_vs_pool":0.0,"tao_pool":4491.0},"116":{"name":"Memo","price":0.027416202,"equilibrium":0.009502450896142454,"distance_pct":188.5,"emission_enabled":false,"cb_vs_pool":0.0,"tao_pool":3073.0},"117":{"name":"glyph","price":0.004095138,"equilibrium":0.0031878408102338444,"distance_pct":28.5,"emission_enabled":true,"cb_vs_pool":0.0,"tao_pool":3595.0},"118":{"name":"Ditto","price":0.014129233,"equilibrium":0.010998457395650979,"distance_pct":28.5,"emission_enabled":true,"cb_vs_pool":0.6,"tao_pool":7537.0},"119":{"name":"Satori","price":0.004021617,"equilibrium":0.0031039853892467694,"distance_pct":29.6,"emission_enabled":false,"cb_vs_pool":0.0,"tao_pool":4095.0},"120":{"name":"Affine","price":0.053054161,"equilibrium":0.056006526437711604,"distance_pct":-5.3,"emission_enabled":true,"cb_vs_pool":0.25,"tao_pool":77491.0},"121":{"name":"sundae_bar","price":0.005404339,"equilibrium":0.005914214921085819,"distance_pct":-8.6,"emission_enabled":true,"cb_vs_pool":0.0,"tao_pool":6822.0},"122":{"name":"CookingTAO","price":0.008140589,"equilibrium":0.002953991089907431,"distance_pct":175.6,"emission_enabled":false,"cb_vs_pool":0.0,"tao_pool":1903.0},"123":{"name":"MANTIS","price":0.003320179,"equilibrium":0.003633019027248436,"distance_pct":-8.6,"emission_enabled":true,"cb_vs_pool":0.08,"tao_pool":6745.0},"124":{"name":"Swarm","price":0.010070028,"equilibrium":0.011779213726285953,"distance_pct":-14.5,"emission_enabled":true,"cb_vs_pool":0.09,"tao_pool":11578.0},"125":{"name":"8 Ball","price":0.003530285,"equilibrium":0.00388551774185656,"distance_pct":-9.1,"emission_enabled":false,"cb_vs_pool":0.0,"tao_pool":6156.0},"126":{"name":"Poker44","price":0.006847498,"equilibrium":0.003708511252421425,"distance_pct":84.6,"emission_enabled":true,"cb_vs_pool":0.56,"tao_pool":2886.0},"127":{"name":"Astrid","price":0.003816724,"equilibrium":0.004033421414063212,"distance_pct":-5.4,"emission_enabled":true,"cb_vs_pool":0.0,"tao_pool":3865.0},"128":{"name":"ByteLeap","price":0.003810329,"equilibrium":0.004142550318652586,"distance_pct":-8.0,"emission_enabled":false,"cb_vs_pool":0.0,"tao_pool":4672.0}}}