{"timestamp":"2026-07-21T18:10:02.584678+00:00","block":8671779,"sum_prices":2.322542233,"subnets":{"1":{"name":"Apex","price":0.008586963,"equilibrium":0.012182616754559929,"distance_pct":-29.5,"emission_enabled":true,"cb_vs_pool":0.0,"tao_pool":26128.0},"2":{"name":"DSperse","price":0.004894619,"equilibrium":0.006795219450864326,"distance_pct":-28.0,"emission_enabled":true,"cb_vs_pool":0.0,"tao_pool":9753.0},"3":{"name":"deprecated","price":0.022326295,"equilibrium":0.03217348753467351,"distance_pct":-30.6,"emission_enabled":true,"cb_vs_pool":0.13,"tao_pool":68985.0},"4":{"name":"Targon","price":0.054659819,"equilibrium":0.0808247078478618,"distance_pct":-32.4,"emission_enabled":true,"cb_vs_pool":0.17,"tao_pool":133034.0},"5":{"name":"Hone","price":0.014315734,"equilibrium":0.019896497633958357,"distance_pct":-28.0,"emission_enabled":false,"cb_vs_pool":0.0,"tao_pool":34789.0},"6":{"name":"Numinous","price":0.003407574,"equilibrium":0.004745979754916651,"distance_pct":-28.2,"emission_enabled":true,"cb_vs_pool":0.15,"tao_pool":9012.0},"7":{"name":"Allways","price":0.004010234,"equilibrium":0.00522248929535264,"distance_pct":-23.2,"emission_enabled":true,"cb_vs_pool":0.06,"tao_pool":7087.0},"8":{"name":"Vanta","price":0.028446257,"equilibrium":0.04105733400208669,"distance_pct":-30.7,"emission_enabled":true,"cb_vs_pool":0.0,"tao_pool":78851.0},"9":{"name":"iota","price":0.034676972,"equilibrium":0.05029860217672298,"distance_pct":-31.1,"emission_enabled":true,"cb_vs_pool":0.0,"tao_pool":61535.0},"10":{"name":"Swap","price":0.005851311,"equilibrium":0.008374434627648072,"distance_pct":-30.1,"emission_enabled":false,"cb_vs_pool":0.0,"tao_pool":15765.0},"11":{"name":"TrajectoryRL","price":0.008145548,"equilibrium":0.011600590105887612,"distance_pct":-29.8,"emission_enabled":true,"cb_vs_pool":0.16,"tao_pool":20205.0},"12":{"name":"Compute Horde","price":0.00547759,"equilibrium":0.008161088197817521,"distance_pct":-32.9,"emission_enabled":false,"cb_vs_pool":0.0,"tao_pool":13552.0},"13":{"name":"Data Universe","price":0.006880332,"equilibrium":0.010002919770682446,"distance_pct":-31.2,"emission_enabled":true,"cb_vs_pool":0.02,"tao_pool":22104.0},"14":{"name":"Cacheon","price":0.010116353,"equilibrium":0.014335604646212328,"distance_pct":-29.4,"emission_enabled":false,"cb_vs_pool":0.0,"tao_pool":26077.0},"15":{"name":"ORO","price":0.020798021,"equilibrium":0.011633823893261954,"distance_pct":78.8,"emission_enabled":true,"cb_vs_pool":0.56,"tao_pool":9130.0},"16":{"name":"Fast Thinker","price":0.004516504,"equilibrium":0.0013187832319476206,"distance_pct":242.5,"emission_enabled":false,"cb_vs_pool":0.0,"tao_pool":714.0},"17":{"name":"404\u2014GEN","price":0.010688888,"equilibrium":0.01524985506300968,"distance_pct":-29.9,"emission_enabled":true,"cb_vs_pool":0.08,"tao_pool":27332.0},"18":{"name":"Zeus","price":0.006864377,"equilibrium":0.009468689617195205,"distance_pct":-27.5,"emission_enabled":true,"cb_vs_pool":0.09,"tao_pool":13075.0},"19":{"name":"blockmachine","price":0.010131648,"equilibrium":0.014490350980534496,"distance_pct":-30.1,"emission_enabled":true,"cb_vs_pool":0.0,"tao_pool":31899.0},"20":{"name":"GroundLayer","price":0.003454959,"equilibrium":0.004917455280440756,"distance_pct":-29.7,"emission_enabled":false,"cb_vs_pool":0.0,"tao_pool":7866.0},"21":{"name":"AdTAO","price":0.004210442,"equilibrium":0.006042769969969742,"distance_pct":-30.3,"emission_enabled":true,"cb_vs_pool":0.05,"tao_pool":8263.0},"22":{"name":"Desearch","price":0.003773206,"equilibrium":0.005486878426165251,"distance_pct":-31.2,"emission_enabled":true,"cb_vs_pool":0.04,"tao_pool":8403.0},"23":{"name":"Trishool","price":0.005916284,"equilibrium":0.008528697654807939,"distance_pct":-30.6,"emission_enabled":true,"cb_vs_pool":0.1,"tao_pool":8706.0},"24":{"name":"Quasar","price":0.008647671,"equilibrium":0.012309751416310747,"distance_pct":-29.7,"emission_enabled":true,"cb_vs_pool":0.27,"tao_pool":12608.0},"25":{"name":"Mainframe","price":0.005670499,"equilibrium":0.008139012143397883,"distance_pct":-30.3,"emission_enabled":false,"cb_vs_pool":0.0,"tao_pool":12174.0},"26":{"name":"Perturb","price":0.006699926,"equilibrium":0.003123473512615662,"distance_pct":114.5,"emission_enabled":false,"cb_vs_pool":0.0,"tao_pool":2710.0},"27":{"name":"Orion","price":0.004254919,"equilibrium":0.006206107196482929,"distance_pct":-31.4,"emission_enabled":false,"cb_vs_pool":0.0,"tao_pool":8412.0},"28":{"name":"gm","price":0.015323448,"equilibrium":0.0222275816546206,"distance_pct":-31.1,"emission_enabled":true,"cb_vs_pool":0.05,"tao_pool":18100.0},"29":{"name":"ho\u03c4floa\u03c4","price":0.003359426,"equilibrium":0.0048321342521300565,"distance_pct":-30.5,"emission_enabled":false,"cb_vs_pool":0.0,"tao_pool":9142.0},"30":{"name":"Endure Network","price":0.00423377,"equilibrium":0.006048253565946194,"distance_pct":-30.0,"emission_enabled":false,"cb_vs_pool":0.0,"tao_pool":9488.0},"31":{"name":"rec4ll","price":0.003941468,"equilibrium":0.002446306697510782,"distance_pct":61.1,"emission_enabled":false,"cb_vs_pool":0.0,"tao_pool":1790.0},"32":{"name":"ItsAI","price":0.003460092,"equilibrium":0.005004139766643791,"distance_pct":-30.9,"emission_enabled":true,"cb_vs_pool":0.18,"tao_pool":7663.0},"33":{"name":"ReadyAI","price":0.006070458,"equilibrium":0.007876009123515434,"distance_pct":-22.9,"emission_enabled":true,"cb_vs_pool":0.15,"tao_pool":16300.0},"34":{"name":"BitMind","price":0.01222327,"equilibrium":0.016598913947636244,"distance_pct":-26.4,"emission_enabled":true,"cb_vs_pool":0.14,"tao_pool":34642.0},"35":{"name":"OxMarkets","price":0.003428631,"equilibrium":0.004922703604526853,"distance_pct":-30.4,"emission_enabled":true,"cb_vs_pool":0.17,"tao_pool":8431.0},"36":{"name":"Eirel","price":0.003342568,"equilibrium":0.0014322840763254891,"distance_pct":133.4,"emission_enabled":true,"cb_vs_pool":0.42,"tao_pool":1085.0},"37":{"name":"Aurelius","price":0.003653735,"equilibrium":0.005303347140711484,"distance_pct":-31.1,"emission_enabled":false,"cb_vs_pool":0.0,"tao_pool":8336.0},"38":{"name":"ChronoLLM","price":0.012508417,"equilibrium":0.007419896979468425,"distance_pct":68.6,"emission_enabled":true,"cb_vs_pool":0.66,"tao_pool":4782.0},"39":{"name":"deprecated","price":0.007116721,"equilibrium":0.010352625569599708,"distance_pct":-31.3,"emission_enabled":true,"cb_vs_pool":0.0,"tao_pool":17792.0},"40":{"name":"Ralph","price":0.012148232,"equilibrium":0.003884099620470196,"distance_pct":212.8,"emission_enabled":false,"cb_vs_pool":0.0,"tao_pool":2726.0},"41":{"name":"Almanac","price":0.006160157,"equilibrium":0.00850573360406725,"distance_pct":-27.6,"emission_enabled":true,"cb_vs_pool":0.0,"tao_pool":13799.0},"42":{"name":"Unknown","price":0.003319246,"equilibrium":0.004549512878983638,"distance_pct":-27.0,"emission_enabled":false,"cb_vs_pool":0.0,"tao_pool":8519.0},"43":{"name":"Graphite","price":0.005425969,"equilibrium":0.007836772036981578,"distance_pct":-30.8,"emission_enabled":false,"cb_vs_pool":0.0,"tao_pool":14394.0},"44":{"name":"Score","price":0.03469806,"equilibrium":0.04933900365647622,"distance_pct":-29.7,"emission_enabled":true,"cb_vs_pool":0.16,"tao_pool":62385.0},"45":{"name":"AlphaRidge.ai","price":0.003203843,"equilibrium":0.004450204176913641,"distance_pct":-28.0,"emission_enabled":false,"cb_vs_pool":0.0,"tao_pool":7172.0},"46":{"name":"Zipcode","price":0.006674099,"equilibrium":0.00928556231584208,"distance_pct":-28.1,"emission_enabled":true,"cb_vs_pool":0.12,"tao_pool":11586.0},"47":{"name":"EvolAI","price":0.003438942,"equilibrium":0.001940438200469685,"distance_pct":77.2,"emission_enabled":false,"cb_vs_pool":0.0,"tao_pool":1395.0},"48":{"name":"Quantum Compute","price":0.005577724,"equilibrium":0.007800485822873284,"distance_pct":-28.5,"emission_enabled":true,"cb_vs_pool":0.18,"tao_pool":12136.0},"49":{"name":"Nepher Robotics","price":0.007124601,"equilibrium":0.005200746549163709,"distance_pct":37.0,"emission_enabled":true,"cb_vs_pool":0.65,"tao_pool":3371.0},"50":{"name":"Synth","price":0.005437268,"equilibrium":0.007496263460752043,"distance_pct":-27.5,"emission_enabled":true,"cb_vs_pool":0.07,"tao_pool":11545.0},"51":{"name":"lium.io","price":0.060758746,"equilibrium":0.08553421815890436,"distance_pct":-29.0,"emission_enabled":true,"cb_vs_pool":0.19,"tao_pool":126758.0},"52":{"name":"Dojo","price":0.006687738,"equilibrium":0.009585042515293535,"distance_pct":-30.2,"emission_enabled":false,"cb_vs_pool":0.0,"tao_pool":18424.0},"53":{"name":"engy","price":0.017714493,"equilibrium":0.025305649436979046,"distance_pct":-30.0,"emission_enabled":false,"cb_vs_pool":0.0,"tao_pool":25716.0},"54":{"name":"Yanez MIID","price":0.006105089,"equilibrium":0.008614727599306097,"distance_pct":-29.1,"emission_enabled":true,"cb_vs_pool":0.15,"tao_pool":9752.0},"55":{"name":"NIOME","price":0.003726346,"equilibrium":0.004956259735188329,"distance_pct":-24.8,"emission_enabled":true,"cb_vs_pool":0.19,"tao_pool":7681.0},"56":{"name":"Gradients","price":0.017346459,"equilibrium":0.02493120668887494,"distance_pct":-30.4,"emission_enabled":true,"cb_vs_pool":0.01,"tao_pool":52535.0},"57":{"name":"SN57","price":0.006661552,"equilibrium":0.0029294291583676123,"distance_pct":127.4,"emission_enabled":false,"cb_vs_pool":0.0,"tao_pool":2082.0},"58":{"name":"greevils","price":0.012358687,"equilibrium":0.0033552478388545735,"distance_pct":268.3,"emission_enabled":false,"cb_vs_pool":0.0,"tao_pool":1207.0},"59":{"name":"Babelbit","price":0.003239698,"equilibrium":0.004631828790606925,"distance_pct":-30.1,"emission_enabled":true,"cb_vs_pool":0.21,"tao_pool":6460.0},"60":{"name":"Bitsec.ai","price":0.005067535,"equilibrium":0.006929143501539258,"distance_pct":-26.9,"emission_enabled":true,"cb_vs_pool":0.09,"tao_pool":7783.0},"61":{"name":"RedTeam","price":0.00618899,"equilibrium":0.008968704815011136,"distance_pct":-31.0,"emission_enabled":true,"cb_vs_pool":0.09,"tao_pool":9832.0},"62":{"name":"Ridges","price":0.012276713,"equilibrium":0.016287311045072632,"distance_pct":-24.6,"emission_enabled":false,"cb_vs_pool":0.0,"tao_pool":31368.0},"63":{"name":"Enigma","price":0.008823201,"equilibrium":0.012544101665214233,"distance_pct":-29.7,"emission_enabled":true,"cb_vs_pool":0.23,"tao_pool":15593.0},"64":{"name":"Chutes","price":0.080618602,"equilibrium":0.1189075707882117,"distance_pct":-32.2,"emission_enabled":true,"cb_vs_pool":0.15,"tao_pool":211491.0},"65":{"name":"TAO Private Network","price":0.003540009,"equilibrium":0.005035727243297219,"distance_pct":-29.7,"emission_enabled":true,"cb_vs_pool":0.0,"tao_pool":7210.0},"66":{"name":"ninja","price":0.006293813,"equilibrium":0.008784283300328512,"distance_pct":-28.4,"emission_enabled":true,"cb_vs_pool":0.27,"tao_pool":9625.0},"67":{"name":"Harnyx","price":0.010252638,"equilibrium":0.004772399055340906,"distance_pct":114.8,"emission_enabled":true,"cb_vs_pool":0.22,"tao_pool":3681.0},"68":{"name":"NOVA","price":0.021647035,"equilibrium":0.030096753277098567,"distance_pct":-28.1,"emission_enabled":true,"cb_vs_pool":0.2,"tao_pool":42976.0},"69":{"name":"Herald","price":0.011508282,"equilibrium":0.006131816515498125,"distance_pct":87.7,"emission_enabled":false,"cb_vs_pool":0.0,"tao_pool":5049.0},"70":{"name":"NexisGen","price":0.002464657,"equilibrium":0.0011104143696450332,"distance_pct":122.0,"emission_enabled":false,"cb_vs_pool":0.0,"tao_pool":990.0},"71":{"name":"Leadpoet","price":0.005077215,"equilibrium":0.007025107374504949,"distance_pct":-27.7,"emission_enabled":true,"cb_vs_pool":0.27,"tao_pool":5638.0},"72":{"name":"StreetVision by NATIX","price":0.003167072,"equilibrium":0.004152248725492541,"distance_pct":-23.7,"emission_enabled":false,"cb_vs_pool":0.0,"tao_pool":7548.0},"73":{"name":"Parked","price":0.003475971,"equilibrium":0.004779981586754661,"distance_pct":-27.3,"emission_enabled":false,"cb_vs_pool":0.0,"tao_pool":7247.0},"74":{"name":"Gittensor","price":0.005374981,"equilibrium":0.006938297908621834,"distance_pct":-22.5,"emission_enabled":true,"cb_vs_pool":0.28,"tao_pool":7618.0},"75":{"name":"Hippius","price":0.015588174,"equilibrium":0.02095099440105959,"distance_pct":-25.6,"emission_enabled":true,"cb_vs_pool":0.0,"tao_pool":30779.0},"76":{"name":"Byzantium","price":0.003021319,"equilibrium":0.0015285311211208968,"distance_pct":97.7,"emission_enabled":false,"cb_vs_pool":0.0,"tao_pool":1227.0},"77":{"name":"Liquidity","price":0.006661221,"equilibrium":0.008912374545294114,"distance_pct":-25.3,"emission_enabled":false,"cb_vs_pool":0.0,"tao_pool":13058.0},"78":{"name":"Vocence","price":0.005133105,"equilibrium":0.0021309971692845347,"distance_pct":140.9,"emission_enabled":true,"cb_vs_pool":0.47,"tao_pool":1475.0},"79":{"name":"MVTRX","price":0.00778154,"equilibrium":0.00976336774065912,"distance_pct":-20.3,"emission_enabled":true,"cb_vs_pool":0.28,"tao_pool":10621.0},"80":{"name":"unknown","price":0.003606617,"equilibrium":0.0022431722949214626,"distance_pct":60.8,"emission_enabled":false,"cb_vs_pool":0.0,"tao_pool":1504.0},"81":{"name":"deprecated","price":0.008710392,"equilibrium":0.01140750439107625,"distance_pct":-23.6,"emission_enabled":true,"cb_vs_pool":0.16,"tao_pool":20904.0},"82":{"name":"Compelle","price":0.006949662,"equilibrium":0.002771655167672568,"distance_pct":150.7,"emission_enabled":true,"cb_vs_pool":0.41,"tao_pool":1993.0},"83":{"name":"CliqueAI","price":0.011371927,"equilibrium":0.010810909160649092,"distance_pct":5.2,"emission_enabled":false,"cb_vs_pool":0.0,"tao_pool":9259.0},"84":{"name":"SN84","price":0.002985887,"equilibrium":0.0013178177286786302,"distance_pct":126.6,"emission_enabled":false,"cb_vs_pool":0.0,"tao_pool":1625.0},"85":{"name":"Vidaio","price":0.006479964,"equilibrium":0.008172258913625633,"distance_pct":-20.7,"emission_enabled":true,"cb_vs_pool":0.18,"tao_pool":13950.0},"86":{"name":"\u2692","price":0.002676651,"equilibrium":0.0018890971889487101,"distance_pct":41.7,"emission_enabled":false,"cb_vs_pool":0.0,"tao_pool":1890.0},"87":{"name":"Provenonce","price":0.005092251,"equilibrium":0.003096637887261141,"distance_pct":64.4,"emission_enabled":false,"cb_vs_pool":0.0,"tao_pool":1868.0},"88":{"name":"Investing","price":0.003392808,"equilibrium":0.0043173851336127085,"distance_pct":-21.4,"emission_enabled":true,"cb_vs_pool":0.21,"tao_pool":6374.0},"89":{"name":"InfiniteQuant","price":0.004026471,"equilibrium":0.004799084733955804,"distance_pct":-16.1,"emission_enabled":true,"cb_vs_pool":0.01,"tao_pool":7006.0},"90":{"name":"KubeTEE AI Factory","price":0.006701818,"equilibrium":0.00439294664290512,"distance_pct":52.6,"emission_enabled":false,"cb_vs_pool":0.0,"tao_pool":1005.0},"91":{"name":"cascade","price":0.013098972,"equilibrium":0.006279886466626927,"distance_pct":108.6,"emission_enabled":false,"cb_vs_pool":0.0,"tao_pool":3806.0},"92":{"name":"wgmi","price":0.006323062,"equilibrium":0.002051922905646251,"distance_pct":208.2,"emission_enabled":false,"cb_vs_pool":0.0,"tao_pool":1249.0},"93":{"name":"Bitcast","price":0.010267556,"equilibrium":0.01268132588998289,"distance_pct":-19.0,"emission_enabled":true,"cb_vs_pool":0.0,"tao_pool":16785.0},"94":{"name":"pending...","price":0.006678066,"equilibrium":0.0043992634367496465,"distance_pct":51.8,"emission_enabled":true,"cb_vs_pool":0.0,"tao_pool":2796.0},"95":{"name":"Actual","price":0.047683778,"equilibrium":0.04397626683762451,"distance_pct":8.4,"emission_enabled":false,"cb_vs_pool":0.0,"tao_pool":29011.0},"96":{"name":"Verathos","price":0.014411663,"equilibrium":0.005833460787046492,"distance_pct":147.1,"emission_enabled":true,"cb_vs_pool":0.0,"tao_pool":3778.0},"97":{"name":"Albedo","price":0.025809375,"equilibrium":0.01224132527976582,"distance_pct":110.8,"emission_enabled":true,"cb_vs_pool":0.54,"tao_pool":9616.0},"98":{"name":"NeverPlayAlone","price":0.003313394,"equilibrium":0.003946504252483184,"distance_pct":-16.0,"emission_enabled":false,"cb_vs_pool":0.0,"tao_pool":5627.0},"99":{"name":"Thirty Spokes","price":0.007040045,"equilibrium":0.0018611822147065126,"distance_pct":278.3,"emission_enabled":false,"cb_vs_pool":0.0,"tao_pool":876.0},"100":{"name":"BASE","price":0.007445137,"equilibrium":0.005081789287782471,"distance_pct":46.5,"emission_enabled":true,"cb_vs_pool":0.0,"tao_pool":3312.0},"101":{"name":"Tag101","price":0.005124234,"equilibrium":0.004501506412924587,"distance_pct":13.8,"emission_enabled":false,"cb_vs_pool":0.0,"tao_pool":4210.0},"102":{"name":"ConnitoAI","price":0.009106431,"equilibrium":0.004053240745265271,"distance_pct":124.7,"emission_enabled":true,"cb_vs_pool":0.0,"tao_pool":3503.0},"103":{"name":"Djinn","price":0.00356437,"equilibrium":0.0038231435812655866,"distance_pct":-6.8,"emission_enabled":true,"cb_vs_pool":0.31,"tao_pool":4272.0},"104":{"name":"Masx.ai","price":0.005027242,"equilibrium":0.0059030768963989014,"distance_pct":-14.8,"emission_enabled":false,"cb_vs_pool":0.0,"tao_pool":6510.0},"105":{"name":"Beam","price":0.009794593,"equilibrium":0.0072443497206891045,"distance_pct":35.2,"emission_enabled":true,"cb_vs_pool":0.56,"tao_pool":5317.0},"106":{"name":"Nodexo","price":0.004059298,"equilibrium":0.004821424148250487,"distance_pct":-15.8,"emission_enabled":true,"cb_vs_pool":0.01,"tao_pool":7673.0},"107":{"name":"Minos","price":0.04419431,"equilibrium":0.024314758161093436,"distance_pct":81.8,"emission_enabled":true,"cb_vs_pool":0.78,"tao_pool":13624.0},"108":{"name":"TalkHead","price":0.00392929,"equilibrium":0.002579837478392995,"distance_pct":52.3,"emission_enabled":false,"cb_vs_pool":0.0,"tao_pool":2202.0},"109":{"name":"GuardArena","price":0.003329363,"equilibrium":0.001977417294200691,"distance_pct":68.4,"emission_enabled":false,"cb_vs_pool":0.0,"tao_pool":1509.0},"110":{"name":"Green Compute","price":0.007705731,"equilibrium":0.006848002385777817,"distance_pct":12.5,"emission_enabled":false,"cb_vs_pool":0.0,"tao_pool":5179.0},"111":{"name":"Claims","price":0.005796968,"equilibrium":0.006840004412009039,"distance_pct":-15.2,"emission_enabled":false,"cb_vs_pool":0.0,"tao_pool":6297.0},"112":{"name":"minotaur","price":0.004180557,"equilibrium":0.003783387055240425,"distance_pct":10.5,"emission_enabled":true,"cb_vs_pool":0.2,"tao_pool":4586.0},"113":{"name":"TensorUSD","price":0.003684297,"equilibrium":0.002386987161518928,"distance_pct":54.3,"emission_enabled":false,"cb_vs_pool":0.0,"tao_pool":2208.0},"114":{"name":"SOMA","price":0.013454074,"equilibrium":0.007757189921548966,"distance_pct":73.4,"emission_enabled":true,"cb_vs_pool":0.66,"tao_pool":4880.0},"115":{"name":"HashiChain","price":0.004197964,"equilibrium":0.00337310724165671,"distance_pct":24.5,"emission_enabled":false,"cb_vs_pool":0.0,"tao_pool":4505.0},"116":{"name":"Memo","price":0.029639209,"equilibrium":0.01012739115944802,"distance_pct":192.7,"emission_enabled":false,"cb_vs_pool":0.0,"tao_pool":3195.0},"117":{"name":"glyph","price":0.00442798,"equilibrium":0.0034191186657794334,"distance_pct":29.5,"emission_enabled":true,"cb_vs_pool":0.17,"tao_pool":3735.0},"118":{"name":"Ditto","price":0.015983718,"equilibrium":0.012312664419310225,"distance_pct":29.8,"emission_enabled":true,"cb_vs_pool":0.63,"tao_pool":7955.0},"119":{"name":"Satori","price":0.00412918,"equilibrium":0.0031573319658263935,"distance_pct":30.8,"emission_enabled":false,"cb_vs_pool":0.0,"tao_pool":4150.0},"120":{"name":"Affine","price":0.053645968,"equilibrium":0.05613415859738351,"distance_pct":-4.4,"emission_enabled":true,"cb_vs_pool":0.26,"tao_pool":77766.0},"121":{"name":"sundae_bar","price":0.006140221,"equilibrium":0.006662497844061185,"distance_pct":-7.8,"emission_enabled":true,"cb_vs_pool":0.0,"tao_pool":7262.0},"122":{"name":"CookingTAO","price":0.008615112,"equilibrium":0.003083348770172154,"distance_pct":179.4,"emission_enabled":false,"cb_vs_pool":0.0,"tao_pool":1958.0},"123":{"name":"MANTIS","price":0.003356444,"equilibrium":0.0036407097257003976,"distance_pct":-7.8,"emission_enabled":true,"cb_vs_pool":0.08,"tao_pool":6772.0},"124":{"name":"Swarm","price":0.008712757,"equilibrium":0.010105465303526802,"distance_pct":-13.8,"emission_enabled":true,"cb_vs_pool":0.09,"tao_pool":10746.0},"125":{"name":"8 Ball","price":0.00354206,"equilibrium":0.0038667922415356166,"distance_pct":-8.4,"emission_enabled":false,"cb_vs_pool":0.0,"tao_pool":6166.0},"126":{"name":"Poker44","price":0.007375422,"equilibrium":0.003942140626189086,"distance_pct":87.1,"emission_enabled":true,"cb_vs_pool":0.58,"tao_pool":2954.0},"127":{"name":"Astrid","price":0.004088135,"equilibrium":0.004282017776247025,"distance_pct":-4.5,"emission_enabled":true,"cb_vs_pool":0.0,"tao_pool":3988.0},"128":{"name":"ByteLeap","price":0.003817838,"equilibrium":0.004116835937476267,"distance_pct":-7.3,"emission_enabled":false,"cb_vs_pool":0.0,"tao_pool":4676.0}}}