{"timestamp":"2026-07-22T08:25:02.789552+00:00","block":8676053,"sum_prices":2.321497962,"subnets":{"1":{"name":"Apex","price":0.008594633,"equilibrium":0.012203369790319848,"distance_pct":-29.6,"emission_enabled":true,"cb_vs_pool":0.0,"tao_pool":26143.0},"2":{"name":"DSperse","price":0.004890457,"equilibrium":0.006795331605721686,"distance_pct":-28.0,"emission_enabled":true,"cb_vs_pool":0.0,"tao_pool":9751.0},"3":{"name":"deprecated","price":0.022326241,"equilibrium":0.032200456716260595,"distance_pct":-30.7,"emission_enabled":true,"cb_vs_pool":0.13,"tao_pool":68999.0},"4":{"name":"Targon","price":0.05470367,"equilibrium":0.08095671517402117,"distance_pct":-32.4,"emission_enabled":true,"cb_vs_pool":0.17,"tao_pool":133122.0},"5":{"name":"Hone","price":0.014339376,"equilibrium":0.01994494861448095,"distance_pct":-28.1,"emission_enabled":false,"cb_vs_pool":0.0,"tao_pool":34818.0},"6":{"name":"Numinous","price":0.003264618,"equilibrium":0.0045508991162869095,"distance_pct":-28.3,"emission_enabled":true,"cb_vs_pool":0.16,"tao_pool":8823.0},"7":{"name":"Allways","price":0.004007846,"equilibrium":0.00522416035225959,"distance_pct":-23.3,"emission_enabled":true,"cb_vs_pool":0.23,"tao_pool":7087.0},"8":{"name":"Vanta","price":0.028448781,"equilibrium":0.04109276338852234,"distance_pct":-30.8,"emission_enabled":true,"cb_vs_pool":0.0,"tao_pool":78858.0},"9":{"name":"iota","price":0.034937405,"equilibrium":0.05071769125243044,"distance_pct":-31.1,"emission_enabled":true,"cb_vs_pool":0.0,"tao_pool":61781.0},"10":{"name":"Swap","price":0.006318429,"equilibrium":0.009049858718549016,"distance_pct":-30.2,"emission_enabled":false,"cb_vs_pool":0.0,"tao_pool":16382.0},"11":{"name":"TrajectoryRL","price":0.008794905,"equilibrium":0.012535990472979248,"distance_pct":-29.8,"emission_enabled":true,"cb_vs_pool":0.16,"tao_pool":21000.0},"12":{"name":"Compute Horde","price":0.005469238,"equilibrium":0.008154615047601907,"distance_pct":-32.9,"emission_enabled":false,"cb_vs_pool":0.0,"tao_pool":13542.0},"13":{"name":"Data Universe","price":0.006874186,"equilibrium":0.010002431959763611,"distance_pct":-31.3,"emission_enabled":true,"cb_vs_pool":0.02,"tao_pool":22099.0},"14":{"name":"Cacheon","price":0.010113362,"equilibrium":0.01434237509146728,"distance_pct":-29.5,"emission_enabled":false,"cb_vs_pool":0.0,"tao_pool":26073.0},"15":{"name":"ORO","price":0.021724074,"equilibrium":0.012179522019863151,"distance_pct":78.4,"emission_enabled":true,"cb_vs_pool":0.54,"tao_pool":9367.0},"16":{"name":"Fast Thinker","price":0.00445425,"equilibrium":0.0013052405652415333,"distance_pct":241.3,"emission_enabled":false,"cb_vs_pool":0.0,"tao_pool":709.0},"17":{"name":"404\u2014GEN","price":0.01076066,"equilibrium":0.015365496824771903,"distance_pct":-30.0,"emission_enabled":true,"cb_vs_pool":0.08,"tao_pool":27431.0},"18":{"name":"Zeus","price":0.006835125,"equilibrium":0.009436771856155934,"distance_pct":-27.6,"emission_enabled":true,"cb_vs_pool":0.09,"tao_pool":13051.0},"19":{"name":"blockmachine","price":0.010163024,"equilibrium":0.014546466573296397,"distance_pct":-30.1,"emission_enabled":true,"cb_vs_pool":0.0,"tao_pool":31949.0},"20":{"name":"GroundLayer","price":0.003514867,"equilibrium":0.005006549599308075,"distance_pct":-29.8,"emission_enabled":false,"cb_vs_pool":0.0,"tao_pool":7934.0},"21":{"name":"AdTAO","price":0.004189789,"equilibrium":0.006018262088807424,"distance_pct":-30.4,"emission_enabled":true,"cb_vs_pool":0.05,"tao_pool":8245.0},"22":{"name":"Desearch","price":0.003756556,"equilibrium":0.005467284523652144,"distance_pct":-31.3,"emission_enabled":true,"cb_vs_pool":0.05,"tao_pool":8387.0},"23":{"name":"Trishool","price":0.005942199,"equilibrium":0.008573364667475098,"distance_pct":-30.7,"emission_enabled":true,"cb_vs_pool":0.1,"tao_pool":8729.0},"24":{"name":"Quasar","price":0.008762765,"equilibrium":0.012484372025078997,"distance_pct":-29.8,"emission_enabled":true,"cb_vs_pool":0.28,"tao_pool":12698.0},"25":{"name":"Mainframe","price":0.005998121,"equilibrium":0.008615790312681549,"distance_pct":-30.4,"emission_enabled":false,"cb_vs_pool":0.0,"tao_pool":12521.0},"26":{"name":"Perturb","price":0.006657082,"equilibrium":0.00311043275280823,"distance_pct":114.0,"emission_enabled":false,"cb_vs_pool":0.0,"tao_pool":2701.0},"27":{"name":"Orion","price":0.004029732,"equilibrium":0.005882049157293295,"distance_pct":-31.5,"emission_enabled":false,"cb_vs_pool":0.0,"tao_pool":8186.0},"28":{"name":"gm","price":0.01490936,"equilibrium":0.02164522020311486,"distance_pct":-31.1,"emission_enabled":true,"cb_vs_pool":0.03,"tao_pool":17863.0},"29":{"name":"ho\u03c4floa\u03c4","price":0.003352168,"equilibrium":0.004825346531030415,"distance_pct":-30.5,"emission_enabled":false,"cb_vs_pool":0.0,"tao_pool":9132.0},"30":{"name":"Endure Network","price":0.004224997,"equilibrium":0.006040321888957711,"distance_pct":-30.1,"emission_enabled":false,"cb_vs_pool":0.0,"tao_pool":9479.0},"31":{"name":"rec4ll","price":0.004021504,"equilibrium":0.002500222797912435,"distance_pct":60.8,"emission_enabled":false,"cb_vs_pool":0.0,"tao_pool":1808.0},"32":{"name":"ItsAI","price":0.003441826,"equilibrium":0.0049818886766128815,"distance_pct":-30.9,"emission_enabled":true,"cb_vs_pool":0.19,"tao_pool":7645.0},"33":{"name":"ReadyAI","price":0.005880239,"equilibrium":0.007636193714107172,"distance_pct":-23.0,"emission_enabled":true,"cb_vs_pool":0.15,"tao_pool":16047.0},"34":{"name":"BitMind","price":0.012220192,"equilibrium":0.016609824941034298,"distance_pct":-26.4,"emission_enabled":true,"cb_vs_pool":0.14,"tao_pool":34646.0},"35":{"name":"OxMarkets","price":0.003352326,"equilibrium":0.004817272090610048,"distance_pct":-30.4,"emission_enabled":true,"cb_vs_pool":0.17,"tao_pool":8339.0},"36":{"name":"Eirel","price":0.003162281,"equilibrium":0.0013598322231997064,"distance_pct":132.5,"emission_enabled":true,"cb_vs_pool":0.51,"tao_pool":1062.0},"37":{"name":"Aurelius","price":0.00364818,"equilibrium":0.005299260718945578,"distance_pct":-31.2,"emission_enabled":false,"cb_vs_pool":0.0,"tao_pool":8330.0},"38":{"name":"ChronoLLM","price":0.01184967,"equilibrium":0.007043019803088289,"distance_pct":68.2,"emission_enabled":true,"cb_vs_pool":0.0,"tao_pool":4661.0},"39":{"name":"deprecated","price":0.007104845,"equilibrium":0.010343096482062821,"distance_pct":-31.3,"emission_enabled":true,"cb_vs_pool":0.0,"tao_pool":17777.0},"40":{"name":"Ralph","price":0.011225552,"equilibrium":0.0036007921227406824,"distance_pct":211.8,"emission_enabled":false,"cb_vs_pool":0.0,"tao_pool":2620.0},"41":{"name":"Almanac","price":0.006154778,"equilibrium":0.008505848824501986,"distance_pct":-27.6,"emission_enabled":true,"cb_vs_pool":0.03,"tao_pool":13796.0},"42":{"name":"Unknown","price":0.003315181,"equilibrium":0.004547544097680016,"distance_pct":-27.1,"emission_enabled":false,"cb_vs_pool":0.0,"tao_pool":8513.0},"43":{"name":"Graphite","price":0.005420159,"equilibrium":0.007834266200990364,"distance_pct":-30.8,"emission_enabled":false,"cb_vs_pool":0.0,"tao_pool":14386.0},"44":{"name":"Score","price":0.034821189,"equilibrium":0.04955696395217365,"distance_pct":-29.7,"emission_enabled":true,"cb_vs_pool":0.16,"tao_pool":62518.0},"45":{"name":"AlphaRidge.ai","price":0.003225478,"equilibrium":0.0044837536976297335,"distance_pct":-28.1,"emission_enabled":false,"cb_vs_pool":0.0,"tao_pool":7196.0},"46":{"name":"Zipcode","price":0.006482922,"equilibrium":0.009027573906144967,"distance_pct":-28.2,"emission_enabled":true,"cb_vs_pool":0.12,"tao_pool":11423.0},"47":{"name":"EvolAI","price":0.003417378,"equilibrium":0.0019318663430221903,"distance_pct":76.9,"emission_enabled":false,"cb_vs_pool":0.0,"tao_pool":1391.0},"48":{"name":"Quantum Compute","price":0.005580415,"equilibrium":0.007811126963893323,"distance_pct":-28.6,"emission_enabled":true,"cb_vs_pool":0.19,"tao_pool":12143.0},"49":{"name":"Nepher Robotics","price":0.006990252,"equilibrium":0.005112017530172018,"distance_pct":36.7,"emission_enabled":true,"cb_vs_pool":0.65,"tao_pool":3348.0},"50":{"name":"Synth","price":0.005435667,"equilibrium":0.007500234240780672,"distance_pct":-27.5,"emission_enabled":true,"cb_vs_pool":0.07,"tao_pool":11547.0},"51":{"name":"lium.io","price":0.060836295,"equilibrium":0.08571822499782383,"distance_pct":-29.0,"emission_enabled":true,"cb_vs_pool":0.2,"tao_pool":126878.0},"52":{"name":"Dojo","price":0.006682691,"equilibrium":0.009585088063097123,"distance_pct":-30.3,"emission_enabled":false,"cb_vs_pool":0.0,"tao_pool":18417.0},"53":{"name":"engy","price":0.021017151,"equilibrium":0.030046401488955456,"distance_pct":-30.1,"emission_enabled":false,"cb_vs_pool":0.0,"tao_pool":27998.0},"54":{"name":"Yanez MIID","price":0.005999865,"equilibrium":0.00847363892373561,"distance_pct":-29.2,"emission_enabled":true,"cb_vs_pool":0.16,"tao_pool":9672.0},"55":{"name":"NIOME","price":0.003697615,"equilibrium":0.004922619789862538,"distance_pct":-24.9,"emission_enabled":true,"cb_vs_pool":0.19,"tao_pool":7654.0},"56":{"name":"Gradients","price":0.017372258,"equilibrium":0.024989658266452212,"distance_pct":-30.5,"emission_enabled":true,"cb_vs_pool":0.01,"tao_pool":52585.0},"57":{"name":"SN57","price":0.006603535,"equilibrium":0.00291082918951561,"distance_pct":126.9,"emission_enabled":false,"cb_vs_pool":0.0,"tao_pool":2073.0},"58":{"name":"greevils","price":0.012177377,"equilibrium":0.003318685058378452,"distance_pct":266.9,"emission_enabled":false,"cb_vs_pool":0.0,"tao_pool":1199.0},"59":{"name":"Babelbit","price":0.003136983,"equilibrium":0.00448883655769924,"distance_pct":-30.1,"emission_enabled":true,"cb_vs_pool":0.21,"tao_pool":6359.0},"60":{"name":"Bitsec.ai","price":0.005208514,"equilibrium":0.007128342152916069,"distance_pct":-26.9,"emission_enabled":true,"cb_vs_pool":0.09,"tao_pool":7894.0},"61":{"name":"RedTeam","price":0.006241416,"equilibrium":0.009052350008611262,"distance_pct":-31.1,"emission_enabled":true,"cb_vs_pool":0.1,"tao_pool":9877.0},"62":{"name":"Ridges","price":0.012237494,"equilibrium":0.01624378338553014,"distance_pct":-24.7,"emission_enabled":false,"cb_vs_pool":0.0,"tao_pool":31317.0},"63":{"name":"Enigma","price":0.008810343,"equilibrium":0.012536667713636042,"distance_pct":-29.7,"emission_enabled":true,"cb_vs_pool":0.23,"tao_pool":15588.0},"64":{"name":"Chutes","price":0.08094667,"equilibrium":0.11949087363142823,"distance_pct":-32.3,"emission_enabled":true,"cb_vs_pool":0.16,"tao_pool":211972.0},"65":{"name":"TAO Private Network","price":0.003395594,"equilibrium":0.0048339909032468235,"distance_pct":-29.8,"emission_enabled":true,"cb_vs_pool":0.0,"tao_pool":7062.0},"66":{"name":"ninja","price":0.006238481,"equilibrium":0.008714088867426062,"distance_pct":-28.4,"emission_enabled":true,"cb_vs_pool":0.27,"tao_pool":9587.0},"67":{"name":"Harnyx","price":0.010174443,"equilibrium":0.004750057177075871,"distance_pct":114.2,"emission_enabled":true,"cb_vs_pool":0.47,"tao_pool":3687.0},"68":{"name":"NOVA","price":0.021711509,"equilibrium":0.030212265015418,"distance_pct":-28.1,"emission_enabled":true,"cb_vs_pool":0.21,"tao_pool":43055.0},"69":{"name":"Herald","price":0.011520852,"equilibrium":0.006150620698462025,"distance_pct":87.3,"emission_enabled":false,"cb_vs_pool":0.0,"tao_pool":5052.0},"70":{"name":"NexisGen","price":0.002877921,"equilibrium":0.0012996184489495427,"distance_pct":121.4,"emission_enabled":false,"cb_vs_pool":0.0,"tao_pool":1070.0},"71":{"name":"Leadpoet","price":0.005093091,"equilibrium":0.007053355603739222,"distance_pct":-27.8,"emission_enabled":true,"cb_vs_pool":0.27,"tao_pool":5651.0},"72":{"name":"StreetVision by NATIX","price":0.003169623,"equilibrium":0.004159029226226818,"distance_pct":-23.8,"emission_enabled":false,"cb_vs_pool":0.0,"tao_pool":7551.0},"73":{"name":"Parked","price":0.003469924,"equilibrium":0.004775437026908205,"distance_pct":-27.3,"emission_enabled":false,"cb_vs_pool":0.0,"tao_pool":7240.0},"74":{"name":"Gittensor","price":0.005386853,"equilibrium":0.0069600149310732684,"distance_pct":-22.6,"emission_enabled":true,"cb_vs_pool":0.28,"tao_pool":7630.0},"75":{"name":"Hippius","price":0.015537613,"equilibrium":0.020900320132568626,"distance_pct":-25.7,"emission_enabled":true,"cb_vs_pool":0.0,"tao_pool":30731.0},"76":{"name":"Byzantium","price":0.003007858,"equilibrium":0.0015248783478985857,"distance_pct":97.3,"emission_enabled":false,"cb_vs_pool":0.0,"tao_pool":1225.0},"77":{"name":"Liquidity","price":0.006631219,"equilibrium":0.008879429425223215,"distance_pct":-25.3,"emission_enabled":false,"cb_vs_pool":0.0,"tao_pool":13028.0},"78":{"name":"Vocence","price":0.005121357,"equilibrium":0.002133969434189213,"distance_pct":140.0,"emission_enabled":true,"cb_vs_pool":0.49,"tao_pool":1485.0},"79":{"name":"MVTRX","price":0.007952262,"equilibrium":0.009986109559360174,"distance_pct":-20.4,"emission_enabled":true,"cb_vs_pool":0.29,"tao_pool":10742.0},"80":{"name":"unknown","price":0.003350872,"equilibrium":0.0020876385755113536,"distance_pct":60.5,"emission_enabled":false,"cb_vs_pool":0.0,"tao_pool":1449.0},"81":{"name":"deprecated","price":0.008762811,"equilibrium":0.011486979718569703,"distance_pct":-23.7,"emission_enabled":true,"cb_vs_pool":0.16,"tao_pool":20973.0},"82":{"name":"Compelle","price":0.006835723,"equilibrium":0.002736816858370377,"distance_pct":149.8,"emission_enabled":true,"cb_vs_pool":0.46,"tao_pool":1992.0},"83":{"name":"CliqueAI","price":0.011349307,"equilibrium":0.010801510652725742,"distance_pct":5.1,"emission_enabled":false,"cb_vs_pool":0.0,"tao_pool":9250.0},"84":{"name":"SN84","price":0.002958814,"equilibrium":0.0013089649715476567,"distance_pct":126.0,"emission_enabled":false,"cb_vs_pool":0.0,"tao_pool":1618.0},"85":{"name":"Vidaio","price":0.006489214,"equilibrium":0.008191967983068388,"distance_pct":-20.8,"emission_enabled":true,"cb_vs_pool":0.18,"tao_pool":13965.0},"86":{"name":"\u2692","price":0.002700323,"equilibrium":0.0019086580387468403,"distance_pct":41.5,"emission_enabled":false,"cb_vs_pool":0.0,"tao_pool":1898.0},"87":{"name":"Provenonce","price":0.005066371,"equilibrium":0.003086234815663849,"distance_pct":64.2,"emission_enabled":false,"cb_vs_pool":0.0,"tao_pool":1863.0},"88":{"name":"Investing","price":0.00337693,"equilibrium":0.004301351633122922,"distance_pct":-21.5,"emission_enabled":true,"cb_vs_pool":0.21,"tao_pool":6362.0},"89":{"name":"InfiniteQuant","price":0.004013141,"equilibrium":0.004788186545796336,"distance_pct":-16.2,"emission_enabled":true,"cb_vs_pool":0.01,"tao_pool":6998.0},"90":{"name":"KubeTEE AI Factory","price":0.006701818,"equilibrium":0.004394922706144814,"distance_pct":52.5,"emission_enabled":false,"cb_vs_pool":0.0,"tao_pool":1005.0},"91":{"name":"cascade","price":0.01337233,"equilibrium":0.006424908601457162,"distance_pct":108.1,"emission_enabled":false,"cb_vs_pool":0.0,"tao_pool":3846.0},"92":{"name":"wgmi","price":0.0062205,"equilibrium":0.002025119769551105,"distance_pct":207.2,"emission_enabled":false,"cb_vs_pool":0.0,"tao_pool":1239.0},"93":{"name":"Bitcast","price":0.010242681,"equilibrium":0.012663322865951482,"distance_pct":-19.1,"emission_enabled":true,"cb_vs_pool":0.03,"tao_pool":16772.0},"94":{"name":"pending...","price":0.006640676,"equilibrium":0.004381638049572985,"distance_pct":51.6,"emission_enabled":true,"cb_vs_pool":0.0,"tao_pool":2788.0},"95":{"name":"Actual","price":0.047732229,"equilibrium":0.04407180940806716,"distance_pct":8.3,"emission_enabled":false,"cb_vs_pool":0.0,"tao_pool":29025.0},"96":{"name":"Verathos","price":0.014157691,"equilibrium":0.005750781045590774,"distance_pct":146.2,"emission_enabled":true,"cb_vs_pool":0.0,"tao_pool":3770.0},"97":{"name":"Albedo","price":0.025470405,"equilibrium":0.012117986162165547,"distance_pct":110.2,"emission_enabled":true,"cb_vs_pool":0.54,"tao_pool":9602.0},"98":{"name":"NeverPlayAlone","price":0.003307022,"equilibrium":0.003942473801559451,"distance_pct":-16.1,"emission_enabled":false,"cb_vs_pool":0.0,"tao_pool":5622.0},"99":{"name":"Thirty Spokes","price":0.006877937,"equilibrium":0.001825430922235426,"distance_pct":276.8,"emission_enabled":false,"cb_vs_pool":0.0,"tao_pool":866.0},"100":{"name":"BASE","price":0.007199249,"equilibrium":0.004921556766999638,"distance_pct":46.3,"emission_enabled":true,"cb_vs_pool":0.0,"tao_pool":3282.0},"101":{"name":"Tag101","price":0.005114487,"equilibrium":0.0044978236921750245,"distance_pct":13.7,"emission_enabled":false,"cb_vs_pool":0.0,"tao_pool":4206.0},"102":{"name":"ConnitoAI","price":0.008902142,"equilibrium":0.003973718307366367,"distance_pct":124.0,"emission_enabled":true,"cb_vs_pool":0.13,"tao_pool":3473.0},"103":{"name":"Djinn","price":0.003352345,"equilibrium":0.003599950071577569,"distance_pct":-6.9,"emission_enabled":true,"cb_vs_pool":0.32,"tao_pool":4148.0},"104":{"name":"Masx.ai","price":0.005020955,"equilibrium":0.005899228665382001,"distance_pct":-14.9,"emission_enabled":false,"cb_vs_pool":0.0,"tao_pool":6506.0},"105":{"name":"Beam","price":0.009608437,"equilibrium":0.007119437431262258,"distance_pct":35.0,"emission_enabled":true,"cb_vs_pool":0.58,"tao_pool":5279.0},"106":{"name":"Nodexo","price":0.004048439,"equilibrium":0.004813572687937004,"distance_pct":-15.9,"emission_enabled":true,"cb_vs_pool":0.01,"tao_pool":7666.0},"107":{"name":"Minos","price":0.044188689,"equilibrium":0.024373213932344175,"distance_pct":81.3,"emission_enabled":true,"cb_vs_pool":0.78,"tao_pool":13697.0},"108":{"name":"TalkHead","price":0.003881138,"equilibrium":0.002552316761989,"distance_pct":52.1,"emission_enabled":false,"cb_vs_pool":0.0,"tao_pool":2189.0},"109":{"name":"GuardArena","price":0.003330294,"equilibrium":0.0019814750772540793,"distance_pct":68.1,"emission_enabled":false,"cb_vs_pool":0.0,"tao_pool":1509.0},"110":{"name":"Green Compute","price":0.00772355,"equilibrium":0.0068720570624765664,"distance_pct":12.4,"emission_enabled":false,"cb_vs_pool":0.0,"tao_pool":5185.0},"111":{"name":"Claims","price":0.005766869,"equilibrium":0.006810693631144365,"distance_pct":-15.3,"emission_enabled":false,"cb_vs_pool":0.0,"tao_pool":6281.0},"112":{"name":"minotaur","price":0.004191404,"equilibrium":0.0037985743455709103,"distance_pct":10.3,"emission_enabled":true,"cb_vs_pool":0.19,"tao_pool":4596.0},"113":{"name":"TensorUSD","price":0.003651568,"equilibrium":0.002369633454947756,"distance_pct":54.1,"emission_enabled":false,"cb_vs_pool":0.0,"tao_pool":2198.0},"114":{"name":"SOMA","price":0.013043915,"equilibrium":0.007538666376825267,"distance_pct":73.0,"emission_enabled":true,"cb_vs_pool":0.7,"tao_pool":4826.0},"115":{"name":"HashiChain","price":0.004202232,"equilibrium":0.0033809942105002947,"distance_pct":24.3,"emission_enabled":false,"cb_vs_pool":0.0,"tao_pool":4507.0},"116":{"name":"Memo","price":0.029134475,"equilibrium":0.009985297451571201,"distance_pct":191.8,"emission_enabled":false,"cb_vs_pool":0.0,"tao_pool":3168.0},"117":{"name":"glyph","price":0.004459162,"equilibrium":0.0034476455210724487,"distance_pct":29.3,"emission_enabled":true,"cb_vs_pool":0.0,"tao_pool":3751.0},"118":{"name":"Ditto","price":0.014865053,"equilibrium":0.011470575328224953,"distance_pct":29.6,"emission_enabled":true,"cb_vs_pool":0.66,"tao_pool":7690.0},"119":{"name":"Satori","price":0.004019869,"equilibrium":0.0030780064276489665,"distance_pct":30.6,"emission_enabled":false,"cb_vs_pool":0.0,"tao_pool":4094.0},"120":{"name":"Affine","price":0.053215698,"equilibrium":0.055749945816517016,"distance_pct":-4.5,"emission_enabled":true,"cb_vs_pool":0.26,"tao_pool":77500.0},"121":{"name":"sundae_bar","price":0.006079599,"equilibrium":0.00660396640039015,"distance_pct":-7.9,"emission_enabled":true,"cb_vs_pool":0.0,"tao_pool":7229.0},"122":{"name":"CookingTAO","price":0.008519731,"equilibrium":0.0030580979599361445,"distance_pct":178.6,"emission_enabled":false,"cb_vs_pool":0.0,"tao_pool":1947.0},"123":{"name":"MANTIS","price":0.003347797,"equilibrium":0.003635543752267778,"distance_pct":-7.9,"emission_enabled":true,"cb_vs_pool":0.08,"tao_pool":6766.0},"124":{"name":"Swarm","price":0.009175051,"equilibrium":0.010653119510960894,"distance_pct":-13.9,"emission_enabled":true,"cb_vs_pool":0.09,"tao_pool":11035.0},"125":{"name":"8 Ball","price":0.003520016,"equilibrium":0.0038465016278023552,"distance_pct":-8.5,"emission_enabled":false,"cb_vs_pool":0.0,"tao_pool":6147.0},"126":{"name":"Poker44","price":0.007248726,"equilibrium":0.0038842217734288533,"distance_pct":86.6,"emission_enabled":true,"cb_vs_pool":0.58,"tao_pool":2941.0},"127":{"name":"Astrid","price":0.003886429,"equilibrium":0.00407565190762758,"distance_pct":-4.6,"emission_enabled":true,"cb_vs_pool":0.0,"tao_pool":3892.0},"128":{"name":"ByteLeap","price":0.003809091,"equilibrium":0.004111486198600715,"distance_pct":-7.4,"emission_enabled":false,"cb_vs_pool":0.0,"tao_pool":4671.0}}}